{
  "name": "418-1 Slave - Donkey",
  "type": "character",
  "img": "modules/hm3-fffv1/images/token/FFF_418-1_Slave.png",
  "items": [
    {
      "name": "Climbing",
      "img": "systems/hm3/images/icons/svg/climbing.svg",
      "type": "skill",
      "_id": "7i1gtcuba0c66og8",
      "effects": [],
      "folder": null,
      "sort": 0,
      "flags": {},
      "system": {
        "notes": "",
        "description": "",
        "source": "",
        "macros": {
          "type": "script",
          "command": ""
        },
        "type": "Physical",
        "skillBase": {
          "value": "10",
          "formula": "",
          "isFormulaValid": true
        },
        "masteryLevel": "47",
        "effectiveMasteryLevel": 0,
        "ritual": {
          "piety": 0
        },
        "improveFlag": false
      },
      "ownership": {
        "default": 0
      },
      "_stats": {
        "systemId": null,
        "systemVersion": null,
        "coreVersion": null,
        "createdTime": null,
        "modifiedTime": null,
        "lastModifiedBy": null
      },
      "_key": "!actors.items!X9QMQDMRJ2tSGvPK.7i1gtcuba0c66og8"
    },
    {
      "type": "skill",
      "img": "systems/hm3/images/icons/svg/muscle.svg",
      "name": "Condition",
      "_id": "pb45je2lwbh32ln7",
      "effects": [],
      "folder": null,
      "sort": 0,
      "flags": {},
      "system": {
        "notes": "",
        "description": "",
        "source": "",
        "macros": {
          "type": "script",
          "command": ""
        },
        "type": "Physical",
        "skillBase": {
          "value": "15",
          "formula": "",
          "isFormulaValid": true
        },
        "masteryLevel": "72",
        "effectiveMasteryLevel": 0,
        "ritual": {
          "piety": 0
        },
        "improveFlag": false
      },
      "ownership": {
        "default": 0
      },
      "_stats": {
        "systemId": null,
        "systemVersion": null,
        "coreVersion": null,
        "createdTime": null,
        "modifiedTime": null,
        "lastModifiedBy": null
      },
      "_key": "!actors.items!X9QMQDMRJ2tSGvPK.pb45je2lwbh32ln7"
    },
    {
      "img": "systems/hm3/images/icons/svg/jump.svg",
      "name": "Jumping",
      "type": "skill",
      "_id": "5bghg2l319a7nh2j",
      "effects": [],
      "folder": null,
      "sort": 0,
      "flags": {},
      "system": {
        "notes": "",
        "description": "",
        "source": "",
        "macros": {
          "type": "script",
          "command": ""
        },
        "type": "Physical",
        "skillBase": {
          "value": "15",
          "formula": "",
          "isFormulaValid": true
        },
        "masteryLevel": "65",
        "effectiveMasteryLevel": 0,
        "ritual": {
          "piety": 0
        },
        "improveFlag": false
      },
      "ownership": {
        "default": 0
      },
      "_stats": {
        "systemId": null,
        "systemVersion": null,
        "coreVersion": null,
        "createdTime": null,
        "modifiedTime": null,
        "lastModifiedBy": null
      },
      "_key": "!actors.items!X9QMQDMRJ2tSGvPK.5bghg2l319a7nh2j"
    },
    {
      "type": "skill",
      "img": "systems/hm3/images/icons/svg/stealth.svg",
      "name": "Stealth",
      "_id": "850oy45g4bf41r1n",
      "effects": [],
      "folder": null,
      "sort": 0,
      "flags": {},
      "system": {
        "notes": "",
        "description": "",
        "source": "",
        "macros": {
          "type": "script",
          "command": ""
        },
        "type": "Physical",
        "skillBase": {
          "value": "17",
          "formula": "",
          "isFormulaValid": true
        },
        "masteryLevel": "57",
        "effectiveMasteryLevel": 0,
        "ritual": {
          "piety": 0
        },
        "improveFlag": false
      },
      "ownership": {
        "default": 0
      },
      "_stats": {
        "systemId": null,
        "systemVersion": null,
        "coreVersion": null,
        "createdTime": null,
        "modifiedTime": null,
        "lastModifiedBy": null
      },
      "_key": "!actors.items!X9QMQDMRJ2tSGvPK.850oy45g4bf41r1n"
    },
    {
      "img": "systems/hm3/images/icons/svg/throw.svg",
      "name": "Throwing",
      "type": "skill",
      "_id": "ucv69gu5eotozjtl",
      "effects": [],
      "folder": null,
      "sort": 0,
      "flags": {},
      "system": {
        "notes": "",
        "description": "",
        "source": "",
        "macros": {
          "type": "script",
          "command": ""
        },
        "type": "Physical",
        "skillBase": {
          "value": "11",
          "formula": "",
          "isFormulaValid": true
        },
        "masteryLevel": "49",
        "effectiveMasteryLevel": 0,
        "ritual": {
          "piety": 0
        },
        "improveFlag": false
      },
      "ownership": {
        "default": 0
      },
      "_stats": {
        "systemId": null,
        "systemVersion": null,
        "coreVersion": null,
        "createdTime": null,
        "modifiedTime": null,
        "lastModifiedBy": null
      },
      "_key": "!actors.items!X9QMQDMRJ2tSGvPK.ucv69gu5eotozjtl"
    },
    {
      "name": "Awareness",
      "img": "systems/hm3/images/icons/svg/awareness.svg",
      "type": "skill",
      "_id": "wpykki5u1u8u1qdp",
      "effects": [],
      "folder": null,
      "sort": 0,
      "flags": {},
      "system": {
        "notes": "",
        "description": "",
        "source": "",
        "macros": {
          "type": "script",
          "command": ""
        },
        "type": "Communication",
        "skillBase": {
          "value": "14",
          "formula": "",
          "isFormulaValid": true
        },
        "masteryLevel": "76",
        "effectiveMasteryLevel": 0,
        "ritual": {
          "piety": 0
        },
        "improveFlag": false
      },
      "ownership": {
        "default": 0
      },
      "_stats": {
        "systemId": null,
        "systemVersion": null,
        "coreVersion": null,
        "createdTime": null,
        "modifiedTime": null,
        "lastModifiedBy": null
      },
      "_key": "!actors.items!X9QMQDMRJ2tSGvPK.wpykki5u1u8u1qdp"
    },
    {
      "img": "systems/hm3/images/icons/svg/cloak-dagger.svg",
      "name": "Intrigue",
      "type": "skill",
      "_id": "wakp0bwchza2jh19",
      "effects": [],
      "folder": null,
      "sort": 0,
      "flags": {},
      "system": {
        "notes": "",
        "description": "",
        "source": "",
        "macros": {
          "type": "script",
          "command": ""
        },
        "type": "Communication",
        "skillBase": {
          "value": "11",
          "formula": "",
          "isFormulaValid": true
        },
        "masteryLevel": "45",
        "effectiveMasteryLevel": 0,
        "ritual": {
          "piety": 0
        },
        "improveFlag": false
      },
      "ownership": {
        "default": 0
      },
      "_stats": {
        "systemId": null,
        "systemVersion": null,
        "coreVersion": null,
        "createdTime": null,
        "modifiedTime": null,
        "lastModifiedBy": null
      },
      "_key": "!actors.items!X9QMQDMRJ2tSGvPK.wakp0bwchza2jh19"
    },
    {
      "type": "skill",
      "name": "Oratory",
      "img": "systems/hm3/images/icons/svg/oratory.svg",
      "_id": "65fog7uv8psf14pn",
      "effects": [],
      "folder": null,
      "sort": 0,
      "flags": {},
      "system": {
        "notes": "",
        "description": "",
        "source": "",
        "macros": {
          "type": "script",
          "command": ""
        },
        "type": "Communication",
        "skillBase": {
          "value": "11",
          "formula": "",
          "isFormulaValid": true
        },
        "masteryLevel": "29",
        "effectiveMasteryLevel": 0,
        "ritual": {
          "piety": 0
        },
        "improveFlag": false
      },
      "ownership": {
        "default": 0
      },
      "_stats": {
        "systemId": null,
        "systemVersion": null,
        "coreVersion": null,
        "createdTime": null,
        "modifiedTime": null,
        "lastModifiedBy": null
      },
      "_key": "!actors.items!X9QMQDMRJ2tSGvPK.65fog7uv8psf14pn"
    },
    {
      "type": "skill",
      "name": "Rhetoric",
      "img": "systems/hm3/images/icons/svg/rhetoric.svg",
      "_id": "qr7uk8xmir815pgg",
      "effects": [],
      "folder": null,
      "sort": 0,
      "flags": {},
      "system": {
        "notes": "",
        "description": "",
        "source": "",
        "macros": {
          "type": "script",
          "command": ""
        },
        "type": "Communication",
        "skillBase": {
          "value": "13",
          "formula": "",
          "isFormulaValid": true
        },
        "masteryLevel": "46",
        "effectiveMasteryLevel": 0,
        "ritual": {
          "piety": 0
        },
        "improveFlag": false
      },
      "ownership": {
        "default": 0
      },
      "_stats": {
        "systemId": null,
        "systemVersion": null,
        "coreVersion": null,
        "createdTime": null,
        "modifiedTime": null,
        "lastModifiedBy": null
      },
      "_key": "!actors.items!X9QMQDMRJ2tSGvPK.qr7uk8xmir815pgg"
    },
    {
      "img": "systems/hm3/images/icons/svg/musician-singing.svg",
      "name": "Singing",
      "type": "skill",
      "_id": "ku7w158sgube8ewr",
      "effects": [],
      "folder": null,
      "sort": 0,
      "flags": {},
      "system": {
        "notes": "",
        "description": "",
        "source": "",
        "macros": {
          "type": "script",
          "command": ""
        },
        "type": "Communication",
        "skillBase": {
          "value": "13",
          "formula": "",
          "isFormulaValid": true
        },
        "masteryLevel": "49",
        "effectiveMasteryLevel": 0,
        "ritual": {
          "piety": 0
        },
        "improveFlag": false
      },
      "ownership": {
        "default": 0
      },
      "_stats": {
        "systemId": null,
        "systemVersion": null,
        "coreVersion": null,
        "createdTime": null,
        "modifiedTime": null,
        "lastModifiedBy": null
      },
      "_key": "!actors.items!X9QMQDMRJ2tSGvPK.ku7w158sgube8ewr"
    },
    {
      "img": "systems/hm3/images/icons/svg/speaking.svg",
      "name": "Language: Hârnic",
      "type": "skill",
      "_id": "3e9kp9i1lzm5z6fl",
      "effects": [],
      "folder": null,
      "sort": 0,
      "flags": {},
      "system": {
        "notes": "",
        "description": "",
        "source": "",
        "macros": {
          "type": "script",
          "command": ""
        },
        "type": "Communication",
        "skillBase": {
          "value": "13",
          "formula": "",
          "isFormulaValid": true
        },
        "masteryLevel": "63",
        "effectiveMasteryLevel": 0,
        "ritual": {
          "piety": 0
        },
        "improveFlag": false
      },
      "ownership": {
        "default": 0
      },
      "_stats": {
        "systemId": null,
        "systemVersion": null,
        "coreVersion": null,
        "createdTime": null,
        "modifiedTime": null,
        "lastModifiedBy": null
      },
      "_key": "!actors.items!X9QMQDMRJ2tSGvPK.3e9kp9i1lzm5z6fl"
    },
    {
      "img": "systems/hm3/images/icons/png/peoni.png",
      "name": "Peoni",
      "type": "skill",
      "_id": "rosy8z7y47jj05n4",
      "effects": [],
      "folder": null,
      "sort": 0,
      "flags": {},
      "system": {
        "notes": "",
        "description": "",
        "source": "",
        "macros": {
          "type": "script",
          "command": ""
        },
        "type": "Ritual",
        "skillBase": {
          "value": "10",
          "formula": "",
          "isFormulaValid": true
        },
        "masteryLevel": "10",
        "effectiveMasteryLevel": 0,
        "ritual": {
          "piety": "17"
        },
        "improveFlag": false
      },
      "ownership": {
        "default": 0
      },
      "_stats": {
        "systemId": null,
        "systemVersion": null,
        "coreVersion": null,
        "createdTime": null,
        "modifiedTime": null,
        "lastModifiedBy": null
      },
      "_key": "!actors.items!X9QMQDMRJ2tSGvPK.rosy8z7y47jj05n4"
    },
    {
      "img": "systems/hm3/images/icons/svg/initiative.svg",
      "name": "Initiative",
      "type": "skill",
      "_id": "ngb0xba217dmoyag",
      "effects": [],
      "folder": null,
      "sort": 0,
      "flags": {},
      "system": {
        "notes": "",
        "description": "",
        "source": "",
        "macros": {
          "type": "script",
          "command": ""
        },
        "type": "Combat",
        "skillBase": {
          "value": "14",
          "formula": "",
          "isFormulaValid": true
        },
        "masteryLevel": "72",
        "effectiveMasteryLevel": 0,
        "ritual": {
          "piety": 0
        },
        "improveFlag": false
      },
      "ownership": {
        "default": 0
      },
      "_stats": {
        "systemId": null,
        "systemVersion": null,
        "coreVersion": null,
        "createdTime": null,
        "modifiedTime": null,
        "lastModifiedBy": null
      },
      "_key": "!actors.items!X9QMQDMRJ2tSGvPK.ngb0xba217dmoyag"
    },
    {
      "type": "skill",
      "img": "systems/hm3/images/icons/svg/punch.svg",
      "name": "Unarmed",
      "_id": "o4l96e9zvnfsgxzq",
      "effects": [],
      "folder": null,
      "sort": 0,
      "flags": {},
      "system": {
        "notes": "",
        "description": "",
        "source": "",
        "macros": {
          "type": "script",
          "command": ""
        },
        "type": "Combat",
        "skillBase": {
          "value": "13",
          "formula": "",
          "isFormulaValid": true
        },
        "masteryLevel": "67",
        "effectiveMasteryLevel": 0,
        "ritual": {
          "piety": 0
        },
        "improveFlag": false
      },
      "ownership": {
        "default": 0
      },
      "_stats": {
        "systemId": null,
        "systemVersion": null,
        "coreVersion": null,
        "createdTime": null,
        "modifiedTime": null,
        "lastModifiedBy": null
      },
      "_key": "!actors.items!X9QMQDMRJ2tSGvPK.o4l96e9zvnfsgxzq"
    },
    {
      "name": "Dodge",
      "img": "systems/hm3/images/icons/svg/dodge.svg",
      "type": "skill",
      "_id": "dku1qt1la4sfv3op",
      "effects": [],
      "folder": null,
      "sort": 0,
      "flags": {},
      "system": {
        "notes": "",
        "description": "",
        "source": "",
        "macros": {
          "type": "script",
          "command": ""
        },
        "type": "Combat",
        "skillBase": {
          "value": "15",
          "formula": "",
          "isFormulaValid": true
        },
        "masteryLevel": "81",
        "effectiveMasteryLevel": 0,
        "ritual": {
          "piety": 0
        },
        "improveFlag": false
      },
      "ownership": {
        "default": 0
      },
      "_stats": {
        "systemId": null,
        "systemVersion": null,
        "coreVersion": null,
        "createdTime": null,
        "modifiedTime": null,
        "lastModifiedBy": null
      },
      "_key": "!actors.items!X9QMQDMRJ2tSGvPK.dku1qt1la4sfv3op"
    },
    {
      "name": "Shackles",
      "img": "systems/hm3/images/icons/svg/miscgear.svg",
      "type": "miscgear",
      "_id": "69fwftgcm33jzi97",
      "effects": [],
      "folder": null,
      "sort": 0,
      "flags": {},
      "system": {
        "notes": "",
        "description": "",
        "source": "",
        "macros": {
          "type": "script",
          "command": ""
        },
        "quantity": 1,
        "value": 0,
        "weight": 1,
        "isCarried": true,
        "isEquipped": true,
        "container": "on-person",
        "arcane": {
          "isArtifact": false,
          "isAttuned": false,
          "charges": -1,
          "ego": 0
        }
      },
      "ownership": {
        "default": 0
      },
      "_stats": {
        "systemId": null,
        "systemVersion": null,
        "coreVersion": null,
        "createdTime": null,
        "modifiedTime": null,
        "lastModifiedBy": null
      },
      "_key": "!actors.items!X9QMQDMRJ2tSGvPK.69fwftgcm33jzi97"
    },
    {
      "name": "Cloth Loincloth",
      "img": "systems/hm3/images/icons/svg/armor.svg",
      "type": "armorgear",
      "_id": "b1j62hbavtp50jzi",
      "effects": [],
      "folder": null,
      "sort": 0,
      "flags": {},
      "system": {
        "notes": "Foul",
        "description": "",
        "source": "",
        "macros": {
          "type": "script",
          "command": ""
        },
        "quantity": 1,
        "value": 8,
        "weight": 1.2,
        "isCarried": true,
        "isEquipped": true,
        "container": "on-person",
        "arcane": {
          "isArtifact": false,
          "isAttuned": false,
          "charges": -1,
          "ego": 0
        },
        "material": "Cloth",
        "armorQuality": 0,
        "locations": [
          "Groin"
        ],
        "protection": {
          "blunt": 1,
          "edged": 1,
          "piercing": 1,
          "fire": 1
        },
        "size": 6
      },
      "ownership": {
        "default": 0
      },
      "_stats": {
        "systemId": null,
        "systemVersion": null,
        "coreVersion": null,
        "createdTime": null,
        "modifiedTime": null,
        "lastModifiedBy": null
      },
      "_key": "!actors.items!X9QMQDMRJ2tSGvPK.b1j62hbavtp50jzi"
    },
    {
      "type": "armorlocation",
      "name": "Skull",
      "_id": "hdlt307m21b9ihea",
      "img": "icons/svg/item-bag.svg",
      "effects": [],
      "folder": null,
      "sort": 0,
      "flags": {},
      "system": {
        "layers": "",
        "armorQuality": 0,
        "blunt": 0,
        "edged": 0,
        "piercing": 0,
        "fire": 0,
        "isFumble": false,
        "isStumble": false,
        "isAmputate": false,
        "impactType": "skull",
        "effectiveImpact": {
          "ei1": "M1",
          "ei5": "S2",
          "ei9": "S3",
          "ei13": "K4",
          "ei17": "K5"
        },
        "probWeight": {
          "high": 150,
          "mid": 50,
          "low": 0
        }
      },
      "ownership": {
        "default": 0
      },
      "_stats": {
        "systemId": null,
        "systemVersion": null,
        "coreVersion": null,
        "createdTime": null,
        "modifiedTime": null,
        "lastModifiedBy": null
      },
      "_key": "!actors.items!X9QMQDMRJ2tSGvPK.hdlt307m21b9ihea"
    },
    {
      "name": "Face",
      "type": "armorlocation",
      "_id": "eexrokdz45fb3u6j",
      "img": "icons/svg/item-bag.svg",
      "effects": [],
      "folder": null,
      "sort": 0,
      "flags": {},
      "system": {
        "layers": "",
        "armorQuality": 0,
        "blunt": 0,
        "edged": 0,
        "piercing": 0,
        "fire": 0,
        "isFumble": false,
        "isStumble": false,
        "isAmputate": false,
        "impactType": "face",
        "effectiveImpact": {
          "ei1": "M1",
          "ei5": "S2",
          "ei9": "S3",
          "ei13": "G4",
          "ei17": "K5"
        },
        "probWeight": {
          "high": 150,
          "mid": 50,
          "low": 0
        }
      },
      "ownership": {
        "default": 0
      },
      "_stats": {
        "systemId": null,
        "systemVersion": null,
        "coreVersion": null,
        "createdTime": null,
        "modifiedTime": null,
        "lastModifiedBy": null
      },
      "_key": "!actors.items!X9QMQDMRJ2tSGvPK.eexrokdz45fb3u6j"
    },
    {
      "name": "Neck",
      "type": "armorlocation",
      "_id": "ud4tv4x9sxlz1eja",
      "img": "icons/svg/item-bag.svg",
      "effects": [],
      "folder": null,
      "sort": 0,
      "flags": {},
      "system": {
        "layers": "",
        "armorQuality": 0,
        "blunt": 0,
        "edged": 0,
        "piercing": 0,
        "fire": 0,
        "isFumble": false,
        "isStumble": false,
        "isAmputate": true,
        "impactType": "neck",
        "effectiveImpact": {
          "ei1": "M1",
          "ei5": "S2",
          "ei9": "S3",
          "ei13": "K4",
          "ei17": "K5"
        },
        "probWeight": {
          "high": 150,
          "mid": 50,
          "low": 0
        }
      },
      "ownership": {
        "default": 0
      },
      "_stats": {
        "systemId": null,
        "systemVersion": null,
        "coreVersion": null,
        "createdTime": null,
        "modifiedTime": null,
        "lastModifiedBy": null
      },
      "_key": "!actors.items!X9QMQDMRJ2tSGvPK.ud4tv4x9sxlz1eja"
    },
    {
      "type": "armorlocation",
      "name": "Left Shoulder",
      "_id": "en8sjk2ivvg49tq5",
      "img": "icons/svg/item-bag.svg",
      "effects": [],
      "folder": null,
      "sort": 0,
      "flags": {},
      "system": {
        "layers": "",
        "armorQuality": 0,
        "blunt": 0,
        "edged": 0,
        "piercing": 0,
        "fire": 0,
        "isFumble": true,
        "isStumble": false,
        "isAmputate": false,
        "impactType": "shoulder",
        "effectiveImpact": {
          "ei1": "M1",
          "ei5": "S2",
          "ei9": "S3",
          "ei13": "G4",
          "ei17": "K4"
        },
        "probWeight": {
          "high": 60,
          "mid": 60,
          "low": 0
        }
      },
      "ownership": {
        "default": 0
      },
      "_stats": {
        "systemId": null,
        "systemVersion": null,
        "coreVersion": null,
        "createdTime": null,
        "modifiedTime": null,
        "lastModifiedBy": null
      },
      "_key": "!actors.items!X9QMQDMRJ2tSGvPK.en8sjk2ivvg49tq5"
    },
    {
      "type": "armorlocation",
      "name": "Right Shoulder",
      "_id": "28fw2tsdv69l91xe",
      "img": "icons/svg/item-bag.svg",
      "effects": [],
      "folder": null,
      "sort": 0,
      "flags": {},
      "system": {
        "layers": "",
        "armorQuality": 0,
        "blunt": 0,
        "edged": 0,
        "piercing": 0,
        "fire": 0,
        "isFumble": true,
        "isStumble": false,
        "isAmputate": false,
        "impactType": "shoulder",
        "effectiveImpact": {
          "ei1": "M1",
          "ei5": "S2",
          "ei9": "S3",
          "ei13": "G4",
          "ei17": "K4"
        },
        "probWeight": {
          "high": 60,
          "mid": 60,
          "low": 0
        }
      },
      "ownership": {
        "default": 0
      },
      "_stats": {
        "systemId": null,
        "systemVersion": null,
        "coreVersion": null,
        "createdTime": null,
        "modifiedTime": null,
        "lastModifiedBy": null
      },
      "_key": "!actors.items!X9QMQDMRJ2tSGvPK.28fw2tsdv69l91xe"
    },
    {
      "type": "armorlocation",
      "name": "Left Upper Arm",
      "_id": "pky27i1bxl8tk2r6",
      "img": "icons/svg/item-bag.svg",
      "effects": [],
      "folder": null,
      "sort": 0,
      "flags": {},
      "system": {
        "layers": "",
        "armorQuality": 0,
        "blunt": 0,
        "edged": 0,
        "piercing": 0,
        "fire": 0,
        "isFumble": true,
        "isStumble": false,
        "isAmputate": true,
        "impactType": "upperarm",
        "effectiveImpact": {
          "ei1": "M1",
          "ei5": "M1",
          "ei9": "S2",
          "ei13": "S3",
          "ei17": "G4"
        },
        "probWeight": {
          "high": 60,
          "mid": 30,
          "low": 0
        }
      },
      "ownership": {
        "default": 0
      },
      "_stats": {
        "systemId": null,
        "systemVersion": null,
        "coreVersion": null,
        "createdTime": null,
        "modifiedTime": null,
        "lastModifiedBy": null
      },
      "_key": "!actors.items!X9QMQDMRJ2tSGvPK.pky27i1bxl8tk2r6"
    },
    {
      "name": "Right Upper Arm",
      "type": "armorlocation",
      "_id": "rpcye9tos86ib0jb",
      "img": "icons/svg/item-bag.svg",
      "effects": [],
      "folder": null,
      "sort": 0,
      "flags": {},
      "system": {
        "layers": "",
        "armorQuality": 0,
        "blunt": 0,
        "edged": 0,
        "piercing": 0,
        "fire": 0,
        "isFumble": true,
        "isStumble": false,
        "isAmputate": true,
        "impactType": "upperarm",
        "effectiveImpact": {
          "ei1": "M1",
          "ei5": "M1",
          "ei9": "S2",
          "ei13": "S3",
          "ei17": "G4"
        },
        "probWeight": {
          "high": 60,
          "mid": 30,
          "low": 0
        }
      },
      "ownership": {
        "default": 0
      },
      "_stats": {
        "systemId": null,
        "systemVersion": null,
        "coreVersion": null,
        "createdTime": null,
        "modifiedTime": null,
        "lastModifiedBy": null
      },
      "_key": "!actors.items!X9QMQDMRJ2tSGvPK.rpcye9tos86ib0jb"
    },
    {
      "type": "armorlocation",
      "name": "Left Elbow",
      "_id": "g1hq990stcx1yg4x",
      "img": "icons/svg/item-bag.svg",
      "effects": [],
      "folder": null,
      "sort": 0,
      "flags": {},
      "system": {
        "layers": "",
        "armorQuality": 0,
        "blunt": 0,
        "edged": 0,
        "piercing": 0,
        "fire": 0,
        "isFumble": true,
        "isStumble": false,
        "isAmputate": true,
        "impactType": "elbow",
        "effectiveImpact": {
          "ei1": "M1",
          "ei5": "S2",
          "ei9": "S3",
          "ei13": "G4",
          "ei17": "G5"
        },
        "probWeight": {
          "high": 20,
          "mid": 10,
          "low": 0
        }
      },
      "ownership": {
        "default": 0
      },
      "_stats": {
        "systemId": null,
        "systemVersion": null,
        "coreVersion": null,
        "createdTime": null,
        "modifiedTime": null,
        "lastModifiedBy": null
      },
      "_key": "!actors.items!X9QMQDMRJ2tSGvPK.g1hq990stcx1yg4x"
    },
    {
      "name": "Right Elbow",
      "type": "armorlocation",
      "_id": "xjp983pbzrs5r7pb",
      "img": "icons/svg/item-bag.svg",
      "effects": [],
      "folder": null,
      "sort": 0,
      "flags": {},
      "system": {
        "layers": "",
        "armorQuality": 0,
        "blunt": 0,
        "edged": 0,
        "piercing": 0,
        "fire": 0,
        "isFumble": true,
        "isStumble": false,
        "isAmputate": true,
        "impactType": "elbow",
        "effectiveImpact": {
          "ei1": "M1",
          "ei5": "S2",
          "ei9": "S3",
          "ei13": "G4",
          "ei17": "G5"
        },
        "probWeight": {
          "high": 20,
          "mid": 10,
          "low": 0
        }
      },
      "ownership": {
        "default": 0
      },
      "_stats": {
        "systemId": null,
        "systemVersion": null,
        "coreVersion": null,
        "createdTime": null,
        "modifiedTime": null,
        "lastModifiedBy": null
      },
      "_key": "!actors.items!X9QMQDMRJ2tSGvPK.xjp983pbzrs5r7pb"
    },
    {
      "name": "Left Hand",
      "type": "armorlocation",
      "_id": "dnl9wippb3a2xazl",
      "img": "icons/svg/item-bag.svg",
      "effects": [],
      "folder": null,
      "sort": 0,
      "flags": {},
      "system": {
        "layers": "",
        "armorQuality": 0,
        "blunt": 0,
        "edged": 0,
        "piercing": 0,
        "fire": 0,
        "isFumble": true,
        "isStumble": false,
        "isAmputate": true,
        "impactType": "hand",
        "effectiveImpact": {
          "ei1": "M1",
          "ei5": "S2",
          "ei9": "S3",
          "ei13": "G4",
          "ei17": "G5"
        },
        "probWeight": {
          "high": 20,
          "mid": 20,
          "low": 30
        }
      },
      "ownership": {
        "default": 0
      },
      "_stats": {
        "systemId": null,
        "systemVersion": null,
        "coreVersion": null,
        "createdTime": null,
        "modifiedTime": null,
        "lastModifiedBy": null
      },
      "_key": "!actors.items!X9QMQDMRJ2tSGvPK.dnl9wippb3a2xazl"
    },
    {
      "name": "Right Hand",
      "type": "armorlocation",
      "_id": "h7r8xfdt4n9gfo9c",
      "img": "icons/svg/item-bag.svg",
      "effects": [],
      "folder": null,
      "sort": 0,
      "flags": {},
      "system": {
        "layers": "",
        "armorQuality": 0,
        "blunt": 0,
        "edged": 0,
        "piercing": 0,
        "fire": 0,
        "isFumble": true,
        "isStumble": false,
        "isAmputate": true,
        "impactType": "hand",
        "effectiveImpact": {
          "ei1": "M1",
          "ei5": "S2",
          "ei9": "S3",
          "ei13": "G4",
          "ei17": "G5"
        },
        "probWeight": {
          "high": 20,
          "mid": 20,
          "low": 30
        }
      },
      "ownership": {
        "default": 0
      },
      "_stats": {
        "systemId": null,
        "systemVersion": null,
        "coreVersion": null,
        "createdTime": null,
        "modifiedTime": null,
        "lastModifiedBy": null
      },
      "_key": "!actors.items!X9QMQDMRJ2tSGvPK.h7r8xfdt4n9gfo9c"
    },
    {
      "type": "armorlocation",
      "name": "Thorax",
      "_id": "e6ql8fp6tp25tulh",
      "img": "icons/svg/item-bag.svg",
      "effects": [],
      "folder": null,
      "sort": 0,
      "flags": {},
      "system": {
        "layers": "",
        "armorQuality": 0,
        "blunt": 0,
        "edged": 0,
        "piercing": 0,
        "fire": 0,
        "isFumble": false,
        "isStumble": false,
        "isAmputate": false,
        "impactType": "thorax",
        "effectiveImpact": {
          "ei1": "M1",
          "ei5": "S2",
          "ei9": "S3",
          "ei13": "G4",
          "ei17": "K5"
        },
        "probWeight": {
          "high": 100,
          "mid": 170,
          "low": 70
        }
      },
      "ownership": {
        "default": 0
      },
      "_stats": {
        "systemId": null,
        "systemVersion": null,
        "coreVersion": null,
        "createdTime": null,
        "modifiedTime": null,
        "lastModifiedBy": null
      },
      "_key": "!actors.items!X9QMQDMRJ2tSGvPK.e6ql8fp6tp25tulh"
    },
    {
      "name": "Abdomen",
      "type": "armorlocation",
      "_id": "2zclm5kv8dtf6axu",
      "img": "icons/svg/item-bag.svg",
      "effects": [],
      "folder": null,
      "sort": 0,
      "flags": {},
      "system": {
        "layers": "",
        "armorQuality": 0,
        "blunt": 0,
        "edged": 0,
        "piercing": 0,
        "fire": 0,
        "isFumble": false,
        "isStumble": false,
        "isAmputate": false,
        "impactType": "abdomen",
        "effectiveImpact": {
          "ei1": "M1",
          "ei5": "S2",
          "ei9": "S3",
          "ei13": "K4",
          "ei17": "K5"
        },
        "probWeight": {
          "high": 60,
          "mid": 100,
          "low": 100
        }
      },
      "ownership": {
        "default": 0
      },
      "_stats": {
        "systemId": null,
        "systemVersion": null,
        "coreVersion": null,
        "createdTime": null,
        "modifiedTime": null,
        "lastModifiedBy": null
      },
      "_key": "!actors.items!X9QMQDMRJ2tSGvPK.2zclm5kv8dtf6axu"
    },
    {
      "type": "armorlocation",
      "name": "Groin",
      "_id": "tf14r4wcxte3ahnq",
      "img": "icons/svg/item-bag.svg",
      "effects": [],
      "folder": null,
      "sort": 0,
      "flags": {},
      "system": {
        "layers": "",
        "armorQuality": 0,
        "blunt": 0,
        "edged": 0,
        "piercing": 0,
        "fire": 0,
        "isFumble": false,
        "isStumble": false,
        "isAmputate": true,
        "impactType": "groin",
        "effectiveImpact": {
          "ei1": "M1",
          "ei5": "S2",
          "ei9": "S3",
          "ei13": "G4",
          "ei17": "G5"
        },
        "probWeight": {
          "high": 0,
          "mid": 40,
          "low": 60
        }
      },
      "ownership": {
        "default": 0
      },
      "_stats": {
        "systemId": null,
        "systemVersion": null,
        "coreVersion": null,
        "createdTime": null,
        "modifiedTime": null,
        "lastModifiedBy": null
      },
      "_key": "!actors.items!X9QMQDMRJ2tSGvPK.tf14r4wcxte3ahnq"
    },
    {
      "type": "armorlocation",
      "name": "Left Hip",
      "_id": "uhg06tz7xfck9t0m",
      "img": "icons/svg/item-bag.svg",
      "effects": [],
      "folder": null,
      "sort": 0,
      "flags": {},
      "system": {
        "layers": "",
        "armorQuality": 0,
        "blunt": 0,
        "edged": 0,
        "piercing": 0,
        "fire": 0,
        "isFumble": false,
        "isStumble": true,
        "isAmputate": false,
        "impactType": "hip",
        "effectiveImpact": {
          "ei1": "M1",
          "ei5": "S2",
          "ei9": "S3",
          "ei13": "G4",
          "ei17": "K4"
        },
        "probWeight": {
          "high": 0,
          "mid": 30,
          "low": 70
        }
      },
      "ownership": {
        "default": 0
      },
      "_stats": {
        "systemId": null,
        "systemVersion": null,
        "coreVersion": null,
        "createdTime": null,
        "modifiedTime": null,
        "lastModifiedBy": null
      },
      "_key": "!actors.items!X9QMQDMRJ2tSGvPK.uhg06tz7xfck9t0m"
    },
    {
      "name": "Right Hip",
      "type": "armorlocation",
      "_id": "k2fn0j3kr65hkbrv",
      "img": "icons/svg/item-bag.svg",
      "effects": [],
      "folder": null,
      "sort": 0,
      "flags": {},
      "system": {
        "layers": "",
        "armorQuality": 0,
        "blunt": 0,
        "edged": 0,
        "piercing": 0,
        "fire": 0,
        "isFumble": false,
        "isStumble": true,
        "isAmputate": false,
        "impactType": "hip",
        "effectiveImpact": {
          "ei1": "M1",
          "ei5": "S2",
          "ei9": "S3",
          "ei13": "G4",
          "ei17": "K4"
        },
        "probWeight": {
          "high": 0,
          "mid": 30,
          "low": 70
        }
      },
      "ownership": {
        "default": 0
      },
      "_stats": {
        "systemId": null,
        "systemVersion": null,
        "coreVersion": null,
        "createdTime": null,
        "modifiedTime": null,
        "lastModifiedBy": null
      },
      "_key": "!actors.items!X9QMQDMRJ2tSGvPK.k2fn0j3kr65hkbrv"
    },
    {
      "name": "Left Thigh",
      "type": "armorlocation",
      "_id": "3zesrq4z9gy109v9",
      "img": "icons/svg/item-bag.svg",
      "effects": [],
      "folder": null,
      "sort": 0,
      "flags": {},
      "system": {
        "layers": "",
        "armorQuality": 0,
        "blunt": 0,
        "edged": 0,
        "piercing": 0,
        "fire": 0,
        "isFumble": false,
        "isStumble": true,
        "isAmputate": true,
        "impactType": "thigh",
        "effectiveImpact": {
          "ei1": "M1",
          "ei5": "S2",
          "ei9": "S3",
          "ei13": "G4",
          "ei17": "K4"
        },
        "probWeight": {
          "high": 0,
          "mid": 40,
          "low": 100
        }
      },
      "ownership": {
        "default": 0
      },
      "_stats": {
        "systemId": null,
        "systemVersion": null,
        "coreVersion": null,
        "createdTime": null,
        "modifiedTime": null,
        "lastModifiedBy": null
      },
      "_key": "!actors.items!X9QMQDMRJ2tSGvPK.3zesrq4z9gy109v9"
    },
    {
      "name": "Right Thigh",
      "type": "armorlocation",
      "_id": "vxyg49sks6slxrbb",
      "img": "icons/svg/item-bag.svg",
      "effects": [],
      "folder": null,
      "sort": 0,
      "flags": {},
      "system": {
        "layers": "",
        "armorQuality": 0,
        "blunt": 0,
        "edged": 0,
        "piercing": 0,
        "fire": 0,
        "isFumble": false,
        "isStumble": true,
        "isAmputate": true,
        "impactType": "thigh",
        "effectiveImpact": {
          "ei1": "M1",
          "ei5": "S2",
          "ei9": "S3",
          "ei13": "G4",
          "ei17": "K4"
        },
        "probWeight": {
          "high": 0,
          "mid": 40,
          "low": 100
        }
      },
      "ownership": {
        "default": 0
      },
      "_stats": {
        "systemId": null,
        "systemVersion": null,
        "coreVersion": null,
        "createdTime": null,
        "modifiedTime": null,
        "lastModifiedBy": null
      },
      "_key": "!actors.items!X9QMQDMRJ2tSGvPK.vxyg49sks6slxrbb"
    },
    {
      "type": "armorlocation",
      "name": "Left Knee",
      "_id": "pvzsa01nydjarywr",
      "img": "icons/svg/item-bag.svg",
      "effects": [],
      "folder": null,
      "sort": 0,
      "flags": {},
      "system": {
        "layers": "",
        "armorQuality": 0,
        "blunt": 0,
        "edged": 0,
        "piercing": 0,
        "fire": 0,
        "isFumble": false,
        "isStumble": true,
        "isAmputate": true,
        "impactType": "knee",
        "effectiveImpact": {
          "ei1": "M1",
          "ei5": "S2",
          "ei9": "S3",
          "ei13": "G4",
          "ei17": "G5"
        },
        "probWeight": {
          "high": 0,
          "mid": 10,
          "low": 40
        }
      },
      "ownership": {
        "default": 0
      },
      "_stats": {
        "systemId": null,
        "systemVersion": null,
        "coreVersion": null,
        "createdTime": null,
        "modifiedTime": null,
        "lastModifiedBy": null
      },
      "_key": "!actors.items!X9QMQDMRJ2tSGvPK.pvzsa01nydjarywr"
    },
    {
      "type": "armorlocation",
      "name": "Right Knee",
      "_id": "md8v6qwn7mtw7w3b",
      "img": "icons/svg/item-bag.svg",
      "effects": [],
      "folder": null,
      "sort": 0,
      "flags": {},
      "system": {
        "layers": "",
        "armorQuality": 0,
        "blunt": 0,
        "edged": 0,
        "piercing": 0,
        "fire": 0,
        "isFumble": false,
        "isStumble": true,
        "isAmputate": true,
        "impactType": "knee",
        "effectiveImpact": {
          "ei1": "M1",
          "ei5": "S2",
          "ei9": "S3",
          "ei13": "G4",
          "ei17": "G5"
        },
        "probWeight": {
          "high": 0,
          "mid": 10,
          "low": 40
        }
      },
      "ownership": {
        "default": 0
      },
      "_stats": {
        "systemId": null,
        "systemVersion": null,
        "coreVersion": null,
        "createdTime": null,
        "modifiedTime": null,
        "lastModifiedBy": null
      },
      "_key": "!actors.items!X9QMQDMRJ2tSGvPK.md8v6qwn7mtw7w3b"
    },
    {
      "name": "Left Calf",
      "type": "armorlocation",
      "_id": "dhimwsmyuarktvpk",
      "img": "icons/svg/item-bag.svg",
      "effects": [],
      "folder": null,
      "sort": 0,
      "flags": {},
      "system": {
        "layers": "",
        "armorQuality": 0,
        "blunt": 0,
        "edged": 0,
        "piercing": 0,
        "fire": 0,
        "isFumble": false,
        "isStumble": true,
        "isAmputate": true,
        "impactType": "calf",
        "effectiveImpact": {
          "ei1": "M1",
          "ei5": "M1",
          "ei9": "S2",
          "ei13": "S3",
          "ei17": "G4"
        },
        "probWeight": {
          "high": 0,
          "mid": 30,
          "low": 70
        }
      },
      "ownership": {
        "default": 0
      },
      "_stats": {
        "systemId": null,
        "systemVersion": null,
        "coreVersion": null,
        "createdTime": null,
        "modifiedTime": null,
        "lastModifiedBy": null
      },
      "_key": "!actors.items!X9QMQDMRJ2tSGvPK.dhimwsmyuarktvpk"
    },
    {
      "name": "Right Calf",
      "type": "armorlocation",
      "_id": "wrkuppr7bmoyhauu",
      "img": "icons/svg/item-bag.svg",
      "effects": [],
      "folder": null,
      "sort": 0,
      "flags": {},
      "system": {
        "layers": "",
        "armorQuality": 0,
        "blunt": 0,
        "edged": 0,
        "piercing": 0,
        "fire": 0,
        "isFumble": false,
        "isStumble": true,
        "isAmputate": true,
        "impactType": "calf",
        "effectiveImpact": {
          "ei1": "M1",
          "ei5": "M1",
          "ei9": "S2",
          "ei13": "S3",
          "ei17": "G4"
        },
        "probWeight": {
          "high": 0,
          "mid": 30,
          "low": 70
        }
      },
      "ownership": {
        "default": 0
      },
      "_stats": {
        "systemId": null,
        "systemVersion": null,
        "coreVersion": null,
        "createdTime": null,
        "modifiedTime": null,
        "lastModifiedBy": null
      },
      "_key": "!actors.items!X9QMQDMRJ2tSGvPK.wrkuppr7bmoyhauu"
    },
    {
      "name": "Left Foot",
      "type": "armorlocation",
      "_id": "hqeqt7kage8hqmsu",
      "img": "icons/svg/item-bag.svg",
      "effects": [],
      "folder": null,
      "sort": 0,
      "flags": {},
      "system": {
        "layers": "",
        "armorQuality": 0,
        "blunt": 0,
        "edged": 0,
        "piercing": 0,
        "fire": 0,
        "isFumble": false,
        "isStumble": true,
        "isAmputate": true,
        "impactType": "foot",
        "effectiveImpact": {
          "ei1": "M1",
          "ei5": "S2",
          "ei9": "S3",
          "ei13": "G4",
          "ei17": "G5"
        },
        "probWeight": {
          "high": 0,
          "mid": 20,
          "low": 40
        }
      },
      "ownership": {
        "default": 0
      },
      "_stats": {
        "systemId": null,
        "systemVersion": null,
        "coreVersion": null,
        "createdTime": null,
        "modifiedTime": null,
        "lastModifiedBy": null
      },
      "_key": "!actors.items!X9QMQDMRJ2tSGvPK.hqeqt7kage8hqmsu"
    },
    {
      "name": "Right Foot",
      "type": "armorlocation",
      "_id": "xtntvnbudcik8x1a",
      "img": "icons/svg/item-bag.svg",
      "effects": [],
      "folder": null,
      "sort": 0,
      "flags": {},
      "system": {
        "layers": "",
        "armorQuality": 0,
        "blunt": 0,
        "edged": 0,
        "piercing": 0,
        "fire": 0,
        "isFumble": false,
        "isStumble": true,
        "isAmputate": true,
        "impactType": "foot",
        "effectiveImpact": {
          "ei1": "M1",
          "ei5": "S2",
          "ei9": "S3",
          "ei13": "G4",
          "ei17": "G5"
        },
        "probWeight": {
          "high": 0,
          "mid": 20,
          "low": 40
        }
      },
      "ownership": {
        "default": 0
      },
      "_stats": {
        "systemId": null,
        "systemVersion": null,
        "coreVersion": null,
        "createdTime": null,
        "modifiedTime": null,
        "lastModifiedBy": null
      },
      "_key": "!actors.items!X9QMQDMRJ2tSGvPK.xtntvnbudcik8x1a"
    }
  ],
  "effects": [],
  "folder": null,
  "sort": 0,
  "flags": {},
  "_id": "X9QMQDMRJ2tSGvPK",
  "system": {
    "bioImage": "modules/hm3-fffv1/images/FFF_418-1_Slave.jpg",
    "species": "Human",
    "fatigue": 0,
    "sunsign": "Tai",
    "abilities": {
      "strength": {
        "base": 16
      },
      "stamina": {
        "base": 15
      },
      "dexterity": {
        "base": 7
      },
      "agility": {
        "base": 15
      },
      "intelligence": {
        "base": 10
      },
      "aura": {
        "base": 10
      },
      "will": {
        "base": 14
      },
      "eyesight": {
        "base": 11
      },
      "hearing": {
        "base": 16
      },
      "smell": {
        "base": 16
      },
      "voice": {
        "base": 12
      },
      "comeliness": {
        "base": 11
      },
      "morality": {
        "base": 7
      },
      "endurance": {
        "base": 15
      }
    },
    "move": {
      "base": 15
    },
    "shockIndex": {
      "max": 100,
      "value": 100
    },
    "description": "<table style=\"width: 95%; color: #191813; font-size: 13px;\" border=\"1\"><tbody style=\"box-sizing: border-box;\"><tr><td style=\"width: 145px;\"><strong>Apparent Age</strong></td><td>Adult</td></tr><tr><td style=\"width: 145px;\"><strong>Culture</strong></td><td>Imperial</td></tr><tr><td style=\"width: 145px;\"><strong>Social Class</strong></td><td>Slave</td></tr><tr><td style=\"width: 145px;\"><strong>Height</strong></td><td>5 ft 6 in</td></tr><tr><td style=\"width: 145px;\"><strong>Frame</strong></td><td>Scant</td></tr><tr><td style=\"width: 145px;\"><strong>Weight</strong></td><td>116 lb</td></tr><tr><td style=\"width: 145px;\"><strong>Appearance</strong></td><td>Average</td></tr><tr><td style=\"width: 145px;\"><strong>Hair Colour</strong></td><td>Blond</td></tr><tr><td style=\"width: 145px;\"><strong>Eye Colour</strong></td><td>Blue</td></tr><tr><td style=\"width: 145px;\"><strong>Voice</strong></td><td>Average</td></tr><tr><td style=\"width: 145px;\"><strong>Obvious Medical Traits</strong></td><td>Scars, parasites, pox marks, missing both thumbs</td></tr><tr><td style=\"width: 145px;\"><strong>Apparent Occupation</strong></td><td>Slave</td></tr><tr><td style=\"width: 145px;\"><strong>Apparent Wealth</strong></td><td>None</td></tr><tr><td style=\"width: 145px;\"><strong>Weapons</strong></td><td>None</td></tr><tr><td style=\"width: 145px;\"><strong>Armour</strong></td><td>None</td></tr><tr><td style=\"width: 145px;\"><strong>Companions</strong></td><td>Overseer, other slaves</td></tr><tr><td style=\"width: 145px;\"><strong>Other obvious features</strong></td><td>None</td></tr></tbody></table>",
    "biography": "<table style=\"width: 95%; color: #191813; font-size: 13px;\" border=\"1\"><tbody style=\"box-sizing: border-box;\"><tr><td style=\"width: 145px;\"><strong>Title</strong></td><td>FFF 418-1 Slave</td></tr><tr><td style=\"width: 145px;\"><strong>Birthday</strong></td><td>9 Savor 694</td></tr><tr><td style=\"width: 145px;\"><strong>Appearance</strong></td><td>Age 25, height 5’6”, scant frame, weight 116 lb, average appearance, fair complexion, blonde hair, blue eyes.</td></tr><tr><td style=\"width: 145px;\"><strong>Medical/Psyche</strong></td><td>Scars, parasites, pox marks, both thumbs removed.</td></tr><tr><td style=\"width: 145px;\"><strong>Size</strong></td><td>5</td></tr><tr><td style=\"width: 145px;\"><strong>Armor</strong></td><td>Foul loincloth</td></tr><tr><td style=\"width: 145px;\"><strong>Other Equipment</strong></td><td>Shackles</td></tr><tr><td style=\"width: 145px;\"><strong>Valuables</strong></td><td>0d in coin</td></tr><tr><td style=\"width: 145px;\"><strong>Notes</strong></td><td></td></tr></tbody></table><h2>Biography</h2><p>Donkey has no idea where he was born or even how old he is. He has been a slave as long as he can remember. He does primarily grunt labour. Donkey loads and unloads ships and wagons. He also works as a porter, carrying heavy baskets of goods.  A raiding party from the Order of the Octagonal Pit took Donkey from an Orbaalese colony on the north coast of Hârn when he was barely more than a toddler. He was branded with their distinctive brand. He was too young to be of any sport in the ring so he was sold as a house slave.  Even at the age of five he proved rebellious. He was beaten frequently but kept trying to escape. Finally, both his thumbs were hacked off with a meat cleaver and cauterized with a hot iron. That seemed to calm him down.</p><p>Donkey has passed from owner to owner in exchange or as payment of debt. He has spent most of his life along the great Thard River in Rethem and the Thardic Republic. He has never had much opportunity or time to learn.  He knows little more than the route from the slave cells to the docks and back. Often, he doesn’t even know what town he is in until he gets a chance to ask one of the other slaves.</p><p>As a slave, Donkey is treated like a donkey, which is where his latest master came up with his name. He is fed and watered, worked hard all day, and then put away in a cell at night. Donkey is a strong slave and uses this to dominate many of the other slaves. He is not afraid to fight them for food or a better sleeping area. Donkey is vigilant and quick to dodge out of the line of the overseer’s whip.</p><h2>Adventure Hooks</h2><p>New Here? The PCs get taken prisoner and thrown naked into the cells with the slaves. If the PCs are obviously tougher or stronger than him, Donkey tries to make friends.</p><p>Fight. Donkey has angered his master for the last time and has been sent to the arena to die. The PCs have been captured and are matched against him. They have a distinct advantage as they have thumbs and can grasp weapons. Do they take mercy on this unskilled slave or slaughter him?</p><p>Will a Slave Do? The PCs need pack animals but there has been a run on the market and there are none currently available. The auctioneer asks if the PCs would take this slave off his hands. He is strong and can carry a heavy pannier of goods. He is the last of a large lot and is being sold cheap.</p><h2>Credits</h2><p>This character is taken from “Friends, Foes, and Followers, Vol. 1” on Lythia.com (https://www.lythia.com/game_aides/friends-foes-followers-volume-1/), by Kerry Mould, with illustrations by Richard Luscheck and Juha Makkonen, and is “fanon”, a derivative work of copyrighted material by Columbia Games Inc. and N. Robin Crossby.</p>",
    "macros": {
      "type": "script",
      "command": ""
    },
    "gender": "Male",
    "occupation": "Slave"
  },
  "ownership": {
    "default": 0,
    "GQFkK1Ng8wDWHlCC": 3
  },
  "prototypeToken": {
    "name": "418-1 Slave - Donkey",
    "displayName": 0,
    "actorLink": false,
    "width": 1,
    "height": 1,
    "lockRotation": false,
    "rotation": 0,
    "alpha": 1,
    "disposition": -1,
    "displayBars": 0,
    "bar1": {
      "attribute": "shockIndex"
    },
    "bar2": {
      "attribute": null
    },
    "flags": {},
    "randomImg": false,
    "light": {
      "dim": 0,
      "bright": 0,
      "angle": 360,
      "alpha": 0.25,
      "animation": {
        "speed": 5,
        "intensity": 5,
        "type": null,
        "reverse": false
      },
      "color": null,
      "coloration": 1,
      "attenuation": 0.5,
      "luminosity": 0.5,
      "saturation": 0,
      "contrast": 0,
      "shadows": 0,
      "darkness": {
        "min": 0,
        "max": 1
      }
    },
    "texture": {
      "src": "modules/hm3-fffv1/images/token/FFF_418-1_Slave.png",
      "scaleX": 1,
      "scaleY": 1,
      "offsetX": 0,
      "offsetY": 0,
      "rotation": 0,
      "tint": null
    },
    "sight": {
      "angle": 360,
      "enabled": false,
      "range": 0,
      "brightness": 1,
      "color": null,
      "attenuation": 0.1,
      "saturation": 0,
      "contrast": 0,
      "visionMode": "basic"
    }
  },
  "_stats": {
    "systemId": null,
    "systemVersion": null,
    "coreVersion": null,
    "createdTime": null,
    "modifiedTime": null,
    "lastModifiedBy": null
  },
  "_key": "!actors!X9QMQDMRJ2tSGvPK"
}
