{
  "name": "606-1 Priestess Naveh - Riatha Deherne",
  "type": "character",
  "img": "modules/hm3-fffv1/images/token/FFF_606-1_Priestess_Naveh.png",
  "items": [
    {
      "name": "Acrobatics",
      "type": "skill",
      "img": "systems/hm3/images/icons/svg/acrobatics.svg",
      "_id": "cp5u12gu9avxg8u7",
      "effects": [],
      "folder": null,
      "sort": 0,
      "flags": {},
      "system": {
        "notes": "",
        "description": "",
        "source": "",
        "macros": {
          "type": "script",
          "command": ""
        },
        "type": "Physical",
        "skillBase": {
          "value": "11",
          "formula": "",
          "isFormulaValid": true
        },
        "masteryLevel": "37",
        "effectiveMasteryLevel": 0,
        "ritual": {
          "piety": 0
        },
        "improveFlag": false
      },
      "ownership": {
        "default": 0
      },
      "_stats": {
        "systemId": null,
        "systemVersion": null,
        "coreVersion": null,
        "createdTime": null,
        "modifiedTime": null,
        "lastModifiedBy": null
      },
      "_key": "!actors.items!78QD3CkEWFGwFie3.cp5u12gu9avxg8u7"
    },
    {
      "img": "systems/hm3/images/icons/svg/climbing.svg",
      "type": "skill",
      "name": "Climbing",
      "_id": "1pxpoc7qle58p4vo",
      "effects": [],
      "folder": null,
      "sort": 0,
      "flags": {},
      "system": {
        "notes": "",
        "description": "",
        "source": "",
        "macros": {
          "type": "script",
          "command": ""
        },
        "type": "Physical",
        "skillBase": {
          "value": "10",
          "formula": "",
          "isFormulaValid": true
        },
        "masteryLevel": "48",
        "effectiveMasteryLevel": 0,
        "ritual": {
          "piety": 0
        },
        "improveFlag": false
      },
      "ownership": {
        "default": 0
      },
      "_stats": {
        "systemId": null,
        "systemVersion": null,
        "coreVersion": null,
        "createdTime": null,
        "modifiedTime": null,
        "lastModifiedBy": null
      },
      "_key": "!actors.items!78QD3CkEWFGwFie3.1pxpoc7qle58p4vo"
    },
    {
      "name": "Condition",
      "img": "systems/hm3/images/icons/svg/muscle.svg",
      "type": "skill",
      "_id": "7tsjb4t60rdp3r5l",
      "effects": [],
      "folder": null,
      "sort": 0,
      "flags": {},
      "system": {
        "notes": "",
        "description": "",
        "source": "",
        "macros": {
          "type": "script",
          "command": ""
        },
        "type": "Physical",
        "skillBase": {
          "value": "10",
          "formula": "",
          "isFormulaValid": true
        },
        "masteryLevel": "56",
        "effectiveMasteryLevel": 0,
        "ritual": {
          "piety": 0
        },
        "improveFlag": false
      },
      "ownership": {
        "default": 0
      },
      "_stats": {
        "systemId": null,
        "systemVersion": null,
        "coreVersion": null,
        "createdTime": null,
        "modifiedTime": null,
        "lastModifiedBy": null
      },
      "_key": "!actors.items!78QD3CkEWFGwFie3.7tsjb4t60rdp3r5l"
    },
    {
      "name": "Jumping",
      "type": "skill",
      "img": "systems/hm3/images/icons/svg/jump.svg",
      "_id": "7b1t1tticw4rhczh",
      "effects": [],
      "folder": null,
      "sort": 0,
      "flags": {},
      "system": {
        "notes": "",
        "description": "",
        "source": "",
        "macros": {
          "type": "script",
          "command": ""
        },
        "type": "Physical",
        "skillBase": {
          "value": "11",
          "formula": "",
          "isFormulaValid": true
        },
        "masteryLevel": "49",
        "effectiveMasteryLevel": 0,
        "ritual": {
          "piety": 0
        },
        "improveFlag": false
      },
      "ownership": {
        "default": 0
      },
      "_stats": {
        "systemId": null,
        "systemVersion": null,
        "coreVersion": null,
        "createdTime": null,
        "modifiedTime": null,
        "lastModifiedBy": null
      },
      "_key": "!actors.items!78QD3CkEWFGwFie3.7b1t1tticw4rhczh"
    },
    {
      "name": "Legerdemain",
      "img": "systems/hm3/images/icons/svg/juggler.svg",
      "type": "skill",
      "_id": "w9j3fo38hjie6426",
      "effects": [],
      "folder": null,
      "sort": 0,
      "flags": {},
      "system": {
        "notes": "",
        "description": "",
        "source": "",
        "macros": {
          "type": "script",
          "command": ""
        },
        "type": "Physical",
        "skillBase": {
          "value": "15",
          "formula": "",
          "isFormulaValid": true
        },
        "masteryLevel": "30",
        "effectiveMasteryLevel": 0,
        "ritual": {
          "piety": 0
        },
        "improveFlag": false
      },
      "ownership": {
        "default": 0
      },
      "_stats": {
        "systemId": null,
        "systemVersion": null,
        "coreVersion": null,
        "createdTime": null,
        "modifiedTime": null,
        "lastModifiedBy": null
      },
      "_key": "!actors.items!78QD3CkEWFGwFie3.w9j3fo38hjie6426"
    },
    {
      "type": "skill",
      "img": "systems/hm3/images/icons/svg/stealth.svg",
      "name": "Stealth",
      "_id": "kyvynnoqgtd894bg",
      "effects": [],
      "folder": null,
      "sort": 0,
      "flags": {},
      "system": {
        "notes": "",
        "description": "",
        "source": "",
        "macros": {
          "type": "script",
          "command": ""
        },
        "type": "Physical",
        "skillBase": {
          "value": "13",
          "formula": "",
          "isFormulaValid": true
        },
        "masteryLevel": "68",
        "effectiveMasteryLevel": 0,
        "ritual": {
          "piety": 0
        },
        "improveFlag": false
      },
      "ownership": {
        "default": 0
      },
      "_stats": {
        "systemId": null,
        "systemVersion": null,
        "coreVersion": null,
        "createdTime": null,
        "modifiedTime": null,
        "lastModifiedBy": null
      },
      "_key": "!actors.items!78QD3CkEWFGwFie3.kyvynnoqgtd894bg"
    },
    {
      "type": "skill",
      "img": "systems/hm3/images/icons/svg/throw.svg",
      "name": "Throwing",
      "_id": "wf7dzsgmk8emhlya",
      "effects": [],
      "folder": null,
      "sort": 0,
      "flags": {},
      "system": {
        "notes": "",
        "description": "",
        "source": "",
        "macros": {
          "type": "script",
          "command": ""
        },
        "type": "Physical",
        "skillBase": {
          "value": "12",
          "formula": "",
          "isFormulaValid": true
        },
        "masteryLevel": "53",
        "effectiveMasteryLevel": 0,
        "ritual": {
          "piety": 0
        },
        "improveFlag": false
      },
      "ownership": {
        "default": 0
      },
      "_stats": {
        "systemId": null,
        "systemVersion": null,
        "coreVersion": null,
        "createdTime": null,
        "modifiedTime": null,
        "lastModifiedBy": null
      },
      "_key": "!actors.items!78QD3CkEWFGwFie3.wf7dzsgmk8emhlya"
    },
    {
      "type": "skill",
      "img": "systems/hm3/images/icons/svg/acting.svg",
      "name": "Acting",
      "_id": "oggbckxutd3qbrkx",
      "effects": [],
      "folder": null,
      "sort": 0,
      "flags": {},
      "system": {
        "notes": "",
        "description": "",
        "source": "",
        "macros": {
          "type": "script",
          "command": ""
        },
        "type": "Communication",
        "skillBase": {
          "value": "15",
          "formula": "",
          "isFormulaValid": true
        },
        "masteryLevel": "80",
        "effectiveMasteryLevel": 0,
        "ritual": {
          "piety": 0
        },
        "improveFlag": false
      },
      "ownership": {
        "default": 0
      },
      "_stats": {
        "systemId": null,
        "systemVersion": null,
        "coreVersion": null,
        "createdTime": null,
        "modifiedTime": null,
        "lastModifiedBy": null
      },
      "_key": "!actors.items!78QD3CkEWFGwFie3.oggbckxutd3qbrkx"
    },
    {
      "name": "Awareness",
      "img": "systems/hm3/images/icons/svg/awareness.svg",
      "type": "skill",
      "_id": "uvtg272gn8v9tg9j",
      "effects": [],
      "folder": null,
      "sort": 0,
      "flags": {},
      "system": {
        "notes": "",
        "description": "",
        "source": "",
        "macros": {
          "type": "script",
          "command": ""
        },
        "type": "Communication",
        "skillBase": {
          "value": "13",
          "formula": "",
          "isFormulaValid": true
        },
        "masteryLevel": "61",
        "effectiveMasteryLevel": 0,
        "ritual": {
          "piety": 0
        },
        "improveFlag": false
      },
      "ownership": {
        "default": 0
      },
      "_stats": {
        "systemId": null,
        "systemVersion": null,
        "coreVersion": null,
        "createdTime": null,
        "modifiedTime": null,
        "lastModifiedBy": null
      },
      "_key": "!actors.items!78QD3CkEWFGwFie3.uvtg272gn8v9tg9j"
    },
    {
      "img": "systems/hm3/images/icons/svg/cloak-dagger.svg",
      "type": "skill",
      "name": "Intrigue",
      "_id": "oinaq2z9stam10gu",
      "effects": [],
      "folder": null,
      "sort": 0,
      "flags": {},
      "system": {
        "notes": "",
        "description": "",
        "source": "",
        "macros": {
          "type": "script",
          "command": ""
        },
        "type": "Communication",
        "skillBase": {
          "value": "15",
          "formula": "",
          "isFormulaValid": true
        },
        "masteryLevel": "61",
        "effectiveMasteryLevel": 0,
        "ritual": {
          "piety": 0
        },
        "improveFlag": false
      },
      "ownership": {
        "default": 0
      },
      "_stats": {
        "systemId": null,
        "systemVersion": null,
        "coreVersion": null,
        "createdTime": null,
        "modifiedTime": null,
        "lastModifiedBy": null
      },
      "_key": "!actors.items!78QD3CkEWFGwFie3.oinaq2z9stam10gu"
    },
    {
      "name": "Mental Conflict",
      "img": "systems/hm3/images/icons/svg/mental.svg",
      "type": "skill",
      "_id": "9elk2ji6a4vv0cxd",
      "effects": [],
      "folder": null,
      "sort": 0,
      "flags": {},
      "system": {
        "notes": "",
        "description": "",
        "source": "",
        "macros": {
          "type": "script",
          "command": ""
        },
        "type": "Communication",
        "skillBase": {
          "value": "14",
          "formula": "",
          "isFormulaValid": true
        },
        "masteryLevel": "58",
        "effectiveMasteryLevel": 0,
        "ritual": {
          "piety": 0
        },
        "improveFlag": false
      },
      "ownership": {
        "default": 0
      },
      "_stats": {
        "systemId": null,
        "systemVersion": null,
        "coreVersion": null,
        "createdTime": null,
        "modifiedTime": null,
        "lastModifiedBy": null
      },
      "_key": "!actors.items!78QD3CkEWFGwFie3.9elk2ji6a4vv0cxd"
    },
    {
      "name": "Oratory",
      "type": "skill",
      "img": "systems/hm3/images/icons/svg/oratory.svg",
      "_id": "k7my806th1xe3aoh",
      "effects": [],
      "folder": null,
      "sort": 0,
      "flags": {},
      "system": {
        "notes": "",
        "description": "",
        "source": "",
        "macros": {
          "type": "script",
          "command": ""
        },
        "type": "Communication",
        "skillBase": {
          "value": "14",
          "formula": "",
          "isFormulaValid": true
        },
        "masteryLevel": "44",
        "effectiveMasteryLevel": 0,
        "ritual": {
          "piety": 0
        },
        "improveFlag": false
      },
      "ownership": {
        "default": 0
      },
      "_stats": {
        "systemId": null,
        "systemVersion": null,
        "coreVersion": null,
        "createdTime": null,
        "modifiedTime": null,
        "lastModifiedBy": null
      },
      "_key": "!actors.items!78QD3CkEWFGwFie3.k7my806th1xe3aoh"
    },
    {
      "name": "Rhetoric",
      "img": "systems/hm3/images/icons/svg/rhetoric.svg",
      "type": "skill",
      "_id": "v830upfkx76i1uxl",
      "effects": [],
      "folder": null,
      "sort": 0,
      "flags": {},
      "system": {
        "notes": "",
        "description": "",
        "source": "",
        "macros": {
          "type": "script",
          "command": ""
        },
        "type": "Communication",
        "skillBase": {
          "value": "15",
          "formula": "",
          "isFormulaValid": true
        },
        "masteryLevel": "64",
        "effectiveMasteryLevel": 0,
        "ritual": {
          "piety": 0
        },
        "improveFlag": false
      },
      "ownership": {
        "default": 0
      },
      "_stats": {
        "systemId": null,
        "systemVersion": null,
        "coreVersion": null,
        "createdTime": null,
        "modifiedTime": null,
        "lastModifiedBy": null
      },
      "_key": "!actors.items!78QD3CkEWFGwFie3.v830upfkx76i1uxl"
    },
    {
      "name": "Singing",
      "type": "skill",
      "img": "systems/hm3/images/icons/svg/musician-singing.svg",
      "_id": "j4ilawmhkhy9s9ik",
      "effects": [],
      "folder": null,
      "sort": 0,
      "flags": {},
      "system": {
        "notes": "",
        "description": "",
        "source": "",
        "macros": {
          "type": "script",
          "command": ""
        },
        "type": "Communication",
        "skillBase": {
          "value": "11",
          "formula": "",
          "isFormulaValid": true
        },
        "masteryLevel": "41",
        "effectiveMasteryLevel": 0,
        "ritual": {
          "piety": 0
        },
        "improveFlag": false
      },
      "ownership": {
        "default": 0
      },
      "_stats": {
        "systemId": null,
        "systemVersion": null,
        "coreVersion": null,
        "createdTime": null,
        "modifiedTime": null,
        "lastModifiedBy": null
      },
      "_key": "!actors.items!78QD3CkEWFGwFie3.j4ilawmhkhy9s9ik"
    },
    {
      "name": "Language: Hârnic",
      "img": "systems/hm3/images/icons/svg/speaking.svg",
      "type": "skill",
      "_id": "oonn5284ko9fs48k",
      "effects": [],
      "folder": null,
      "sort": 0,
      "flags": {},
      "system": {
        "notes": "",
        "description": "",
        "source": "",
        "macros": {
          "type": "script",
          "command": ""
        },
        "type": "Communication",
        "skillBase": {
          "value": "14",
          "formula": "",
          "isFormulaValid": true
        },
        "masteryLevel": "74",
        "effectiveMasteryLevel": 0,
        "ritual": {
          "piety": 0
        },
        "improveFlag": false
      },
      "ownership": {
        "default": 0
      },
      "_stats": {
        "systemId": null,
        "systemVersion": null,
        "coreVersion": null,
        "createdTime": null,
        "modifiedTime": null,
        "lastModifiedBy": null
      },
      "_key": "!actors.items!78QD3CkEWFGwFie3.oonn5284ko9fs48k"
    },
    {
      "type": "skill",
      "img": "systems/hm3/images/icons/svg/speaking.svg",
      "name": "Language: Besha",
      "_id": "6wi9otoqkygqtquh",
      "effects": [],
      "folder": null,
      "sort": 0,
      "flags": {},
      "system": {
        "notes": "",
        "description": "",
        "source": "",
        "macros": {
          "type": "script",
          "command": ""
        },
        "type": "Communication",
        "skillBase": {
          "value": "14",
          "formula": "",
          "isFormulaValid": true
        },
        "masteryLevel": "84",
        "effectiveMasteryLevel": 0,
        "ritual": {
          "piety": 0
        },
        "improveFlag": false
      },
      "ownership": {
        "default": 0
      },
      "_stats": {
        "systemId": null,
        "systemVersion": null,
        "coreVersion": null,
        "createdTime": null,
        "modifiedTime": null,
        "lastModifiedBy": null
      },
      "_key": "!actors.items!78QD3CkEWFGwFie3.6wi9otoqkygqtquh"
    },
    {
      "img": "systems/hm3/images/icons/svg/scroll.svg",
      "type": "skill",
      "name": "Script: Lakise",
      "_id": "15tw90v8r6uavtu5",
      "effects": [],
      "folder": null,
      "sort": 0,
      "flags": {},
      "system": {
        "notes": "",
        "description": "",
        "source": "",
        "macros": {
          "type": "script",
          "command": ""
        },
        "type": "Communication",
        "skillBase": {
          "value": "14",
          "formula": "",
          "isFormulaValid": true
        },
        "masteryLevel": "84",
        "effectiveMasteryLevel": 0,
        "ritual": {
          "piety": 0
        },
        "improveFlag": false
      },
      "ownership": {
        "default": 0
      },
      "_stats": {
        "systemId": null,
        "systemVersion": null,
        "coreVersion": null,
        "createdTime": null,
        "modifiedTime": null,
        "lastModifiedBy": null
      },
      "_key": "!actors.items!78QD3CkEWFGwFie3.15tw90v8r6uavtu5"
    },
    {
      "type": "skill",
      "img": "systems/hm3/images/icons/svg/scroll.svg",
      "name": "Script: Neramic",
      "_id": "p3txckrol1wdmt25",
      "effects": [],
      "folder": null,
      "sort": 0,
      "flags": {},
      "system": {
        "notes": "",
        "description": "",
        "source": "",
        "macros": {
          "type": "script",
          "command": ""
        },
        "type": "Communication",
        "skillBase": {
          "value": "14",
          "formula": "",
          "isFormulaValid": true
        },
        "masteryLevel": "84",
        "effectiveMasteryLevel": 0,
        "ritual": {
          "piety": 0
        },
        "improveFlag": false
      },
      "ownership": {
        "default": 0
      },
      "_stats": {
        "systemId": null,
        "systemVersion": null,
        "coreVersion": null,
        "createdTime": null,
        "modifiedTime": null,
        "lastModifiedBy": null
      },
      "_key": "!actors.items!78QD3CkEWFGwFie3.p3txckrol1wdmt25"
    },
    {
      "name": "Naveh",
      "type": "skill",
      "img": "systems/hm3/images/icons/png/naveh.png",
      "_id": "4i2ge2kdg6lt5m2g",
      "effects": [],
      "folder": null,
      "sort": 0,
      "flags": {},
      "system": {
        "notes": "",
        "description": "",
        "source": "",
        "macros": {
          "type": "script",
          "command": ""
        },
        "type": "Ritual",
        "skillBase": {
          "value": "14",
          "formula": "",
          "isFormulaValid": true
        },
        "masteryLevel": "56",
        "effectiveMasteryLevel": 0,
        "ritual": {
          "piety": "70"
        },
        "improveFlag": false
      },
      "ownership": {
        "default": 0
      },
      "_stats": {
        "systemId": null,
        "systemVersion": null,
        "coreVersion": null,
        "createdTime": null,
        "modifiedTime": null,
        "lastModifiedBy": null
      },
      "_key": "!actors.items!78QD3CkEWFGwFie3.4i2ge2kdg6lt5m2g"
    },
    {
      "type": "skill",
      "img": "systems/hm3/images/icons/png/peoni.png",
      "name": "Peoni",
      "_id": "stvzqkoqlvobc31f",
      "effects": [],
      "folder": null,
      "sort": 0,
      "flags": {},
      "system": {
        "notes": "",
        "description": "",
        "source": "",
        "macros": {
          "type": "script",
          "command": ""
        },
        "type": "Ritual",
        "skillBase": {
          "value": "13",
          "formula": "",
          "isFormulaValid": true
        },
        "masteryLevel": "13",
        "effectiveMasteryLevel": 0,
        "ritual": {
          "piety": "0"
        },
        "improveFlag": false
      },
      "ownership": {
        "default": 0
      },
      "_stats": {
        "systemId": null,
        "systemVersion": null,
        "coreVersion": null,
        "createdTime": null,
        "modifiedTime": null,
        "lastModifiedBy": null
      },
      "_key": "!actors.items!78QD3CkEWFGwFie3.stvzqkoqlvobc31f"
    },
    {
      "name": "Initiative",
      "img": "systems/hm3/images/icons/svg/initiative.svg",
      "type": "skill",
      "_id": "6ue0f18xn79bjsix",
      "effects": [],
      "folder": null,
      "sort": 0,
      "flags": {},
      "system": {
        "notes": "",
        "description": "",
        "source": "",
        "macros": {
          "type": "script",
          "command": ""
        },
        "type": "Combat",
        "skillBase": {
          "value": "13",
          "formula": "",
          "isFormulaValid": true
        },
        "masteryLevel": "80",
        "effectiveMasteryLevel": 0,
        "ritual": {
          "piety": 0
        },
        "improveFlag": false
      },
      "ownership": {
        "default": 0
      },
      "_stats": {
        "systemId": null,
        "systemVersion": null,
        "coreVersion": null,
        "createdTime": null,
        "modifiedTime": null,
        "lastModifiedBy": null
      },
      "_key": "!actors.items!78QD3CkEWFGwFie3.6ue0f18xn79bjsix"
    },
    {
      "name": "Unarmed",
      "type": "skill",
      "img": "systems/hm3/images/icons/svg/punch.svg",
      "_id": "t0l5mzj3olscgonl",
      "effects": [],
      "folder": null,
      "sort": 0,
      "flags": {},
      "system": {
        "notes": "",
        "description": "",
        "source": "",
        "macros": {
          "type": "script",
          "command": ""
        },
        "type": "Combat",
        "skillBase": {
          "value": "10",
          "formula": "",
          "isFormulaValid": true
        },
        "masteryLevel": "67",
        "effectiveMasteryLevel": 0,
        "ritual": {
          "piety": 0
        },
        "improveFlag": false
      },
      "ownership": {
        "default": 0
      },
      "_stats": {
        "systemId": null,
        "systemVersion": null,
        "coreVersion": null,
        "createdTime": null,
        "modifiedTime": null,
        "lastModifiedBy": null
      },
      "_key": "!actors.items!78QD3CkEWFGwFie3.t0l5mzj3olscgonl"
    },
    {
      "name": "Dodge",
      "type": "skill",
      "img": "systems/hm3/images/icons/svg/dodge.svg",
      "_id": "2rgkvzh6cudpm7ut",
      "effects": [],
      "folder": null,
      "sort": 0,
      "flags": {},
      "system": {
        "notes": "",
        "description": "",
        "source": "",
        "macros": {
          "type": "script",
          "command": ""
        },
        "type": "Combat",
        "skillBase": {
          "value": "12",
          "formula": "",
          "isFormulaValid": true
        },
        "masteryLevel": "60",
        "effectiveMasteryLevel": 0,
        "ritual": {
          "piety": 0
        },
        "improveFlag": false
      },
      "ownership": {
        "default": 0
      },
      "_stats": {
        "systemId": null,
        "systemVersion": null,
        "coreVersion": null,
        "createdTime": null,
        "modifiedTime": null,
        "lastModifiedBy": null
      },
      "_key": "!actors.items!78QD3CkEWFGwFie3.2rgkvzh6cudpm7ut"
    },
    {
      "img": "systems/hm3/images/icons/svg/dagger.svg",
      "type": "skill",
      "name": "Dagger",
      "_id": "wyjvvo5f7spwrn49",
      "effects": [],
      "folder": null,
      "sort": 0,
      "flags": {},
      "system": {
        "notes": "",
        "description": "",
        "source": "",
        "macros": {
          "type": "script",
          "command": ""
        },
        "type": "Combat",
        "skillBase": {
          "value": "12",
          "formula": "",
          "isFormulaValid": true
        },
        "masteryLevel": "69",
        "effectiveMasteryLevel": 0,
        "ritual": {
          "piety": 0
        },
        "improveFlag": false
      },
      "ownership": {
        "default": 0
      },
      "_stats": {
        "systemId": null,
        "systemVersion": null,
        "coreVersion": null,
        "createdTime": null,
        "modifiedTime": null,
        "lastModifiedBy": null
      },
      "_key": "!actors.items!78QD3CkEWFGwFie3.wyjvvo5f7spwrn49"
    },
    {
      "img": "systems/hm3/images/icons/svg/caduceus.svg",
      "type": "skill",
      "name": "Alchemy",
      "_id": "pqeqwfwuhrf4pogp",
      "effects": [],
      "folder": null,
      "sort": 0,
      "flags": {},
      "system": {
        "notes": "",
        "description": "",
        "source": "",
        "macros": {
          "type": "script",
          "command": ""
        },
        "type": "Craft",
        "skillBase": {
          "value": "14",
          "formula": "",
          "isFormulaValid": true
        },
        "masteryLevel": "38",
        "effectiveMasteryLevel": 0,
        "ritual": {
          "piety": 0
        },
        "improveFlag": false
      },
      "ownership": {
        "default": 0
      },
      "_stats": {
        "systemId": null,
        "systemVersion": null,
        "coreVersion": null,
        "createdTime": null,
        "modifiedTime": null,
        "lastModifiedBy": null
      },
      "_key": "!actors.items!78QD3CkEWFGwFie3.pqeqwfwuhrf4pogp"
    },
    {
      "name": "Brewing",
      "img": "systems/hm3/images/icons/svg/brewing.svg",
      "type": "skill",
      "_id": "54oor6jm9dhfgqf7",
      "effects": [],
      "folder": null,
      "sort": 0,
      "flags": {},
      "system": {
        "notes": "",
        "description": "",
        "source": "",
        "macros": {
          "type": "script",
          "command": ""
        },
        "type": "Craft",
        "skillBase": {
          "value": "13",
          "formula": "",
          "isFormulaValid": true
        },
        "masteryLevel": "47",
        "effectiveMasteryLevel": 0,
        "ritual": {
          "piety": 0
        },
        "improveFlag": false
      },
      "ownership": {
        "default": 0
      },
      "_stats": {
        "systemId": null,
        "systemVersion": null,
        "coreVersion": null,
        "createdTime": null,
        "modifiedTime": null,
        "lastModifiedBy": null
      },
      "_key": "!actors.items!78QD3CkEWFGwFie3.54oor6jm9dhfgqf7"
    },
    {
      "name": "Cookery",
      "type": "skill",
      "img": "systems/hm3/images/icons/svg/cookery.svg",
      "_id": "puto0dvzc354tb5a",
      "effects": [],
      "folder": null,
      "sort": 0,
      "flags": {},
      "system": {
        "notes": "",
        "description": "",
        "source": "",
        "macros": {
          "type": "script",
          "command": ""
        },
        "type": "Craft",
        "skillBase": {
          "value": "13",
          "formula": "",
          "isFormulaValid": true
        },
        "masteryLevel": "79",
        "effectiveMasteryLevel": 0,
        "ritual": {
          "piety": 0
        },
        "improveFlag": false
      },
      "ownership": {
        "default": 0
      },
      "_stats": {
        "systemId": null,
        "systemVersion": null,
        "coreVersion": null,
        "createdTime": null,
        "modifiedTime": null,
        "lastModifiedBy": null
      },
      "_key": "!actors.items!78QD3CkEWFGwFie3.puto0dvzc354tb5a"
    },
    {
      "name": "Drawing",
      "img": "systems/hm3/images/icons/svg/drawing.svg",
      "type": "skill",
      "_id": "y6qfoa67yqic1s6r",
      "effects": [],
      "folder": null,
      "sort": 0,
      "flags": {},
      "system": {
        "notes": "",
        "description": "",
        "source": "",
        "macros": {
          "type": "script",
          "command": ""
        },
        "type": "Craft",
        "skillBase": {
          "value": "12",
          "formula": "",
          "isFormulaValid": true
        },
        "masteryLevel": "27",
        "effectiveMasteryLevel": 0,
        "ritual": {
          "piety": 0
        },
        "improveFlag": false
      },
      "ownership": {
        "default": 0
      },
      "_stats": {
        "systemId": null,
        "systemVersion": null,
        "coreVersion": null,
        "createdTime": null,
        "modifiedTime": null,
        "lastModifiedBy": null
      },
      "_key": "!actors.items!78QD3CkEWFGwFie3.y6qfoa67yqic1s6r"
    },
    {
      "type": "skill",
      "img": "systems/hm3/images/icons/svg/embalming.svg",
      "name": "Embalming",
      "_id": "8mx3lnm2xvg0fcvq",
      "effects": [],
      "folder": null,
      "sort": 0,
      "flags": {},
      "system": {
        "notes": "",
        "description": "",
        "source": "",
        "macros": {
          "type": "script",
          "command": ""
        },
        "type": "Craft",
        "skillBase": {
          "value": "13",
          "formula": "",
          "isFormulaValid": true
        },
        "masteryLevel": "34",
        "effectiveMasteryLevel": 0,
        "ritual": {
          "piety": 0
        },
        "improveFlag": false
      },
      "ownership": {
        "default": 0
      },
      "_stats": {
        "systemId": null,
        "systemVersion": null,
        "coreVersion": null,
        "createdTime": null,
        "modifiedTime": null,
        "lastModifiedBy": null
      },
      "_key": "!actors.items!78QD3CkEWFGwFie3.8mx3lnm2xvg0fcvq"
    },
    {
      "type": "skill",
      "img": "systems/hm3/images/icons/svg/unicorn.svg",
      "name": "Folklore",
      "_id": "8lvh5kjrfj9sw364",
      "effects": [],
      "folder": null,
      "sort": 0,
      "flags": {},
      "system": {
        "notes": "",
        "description": "",
        "source": "",
        "macros": {
          "type": "script",
          "command": ""
        },
        "type": "Craft",
        "skillBase": {
          "value": "15",
          "formula": "",
          "isFormulaValid": true
        },
        "masteryLevel": "50",
        "effectiveMasteryLevel": 0,
        "ritual": {
          "piety": 0
        },
        "improveFlag": false
      },
      "ownership": {
        "default": 0
      },
      "_stats": {
        "systemId": null,
        "systemVersion": null,
        "coreVersion": null,
        "createdTime": null,
        "modifiedTime": null,
        "lastModifiedBy": null
      },
      "_key": "!actors.items!78QD3CkEWFGwFie3.8lvh5kjrfj9sw364"
    },
    {
      "type": "skill",
      "img": "systems/hm3/images/icons/svg/heraldry.svg",
      "name": "Heraldry",
      "_id": "flr925wxbmtyhzbi",
      "effects": [],
      "folder": null,
      "sort": 0,
      "flags": {},
      "system": {
        "notes": "",
        "description": "",
        "source": "",
        "macros": {
          "type": "script",
          "command": ""
        },
        "type": "Craft",
        "skillBase": {
          "value": "13",
          "formula": "",
          "isFormulaValid": true
        },
        "masteryLevel": "29",
        "effectiveMasteryLevel": 0,
        "ritual": {
          "piety": 0
        },
        "improveFlag": false
      },
      "ownership": {
        "default": 0
      },
      "_stats": {
        "systemId": null,
        "systemVersion": null,
        "coreVersion": null,
        "createdTime": null,
        "modifiedTime": null,
        "lastModifiedBy": null
      },
      "_key": "!actors.items!78QD3CkEWFGwFie3.flr925wxbmtyhzbi"
    },
    {
      "name": "Herblore",
      "type": "skill",
      "img": "systems/hm3/images/icons/svg/herblore.svg",
      "_id": "ijcuwwlj96xsl3ll",
      "effects": [],
      "folder": null,
      "sort": 0,
      "flags": {},
      "system": {
        "notes": "",
        "description": "",
        "source": "",
        "macros": {
          "type": "script",
          "command": ""
        },
        "type": "Craft",
        "skillBase": {
          "value": "14",
          "formula": "",
          "isFormulaValid": true
        },
        "masteryLevel": "57",
        "effectiveMasteryLevel": 0,
        "ritual": {
          "piety": 0
        },
        "improveFlag": false
      },
      "ownership": {
        "default": 0
      },
      "_stats": {
        "systemId": null,
        "systemVersion": null,
        "coreVersion": null,
        "createdTime": null,
        "modifiedTime": null,
        "lastModifiedBy": null
      },
      "_key": "!actors.items!78QD3CkEWFGwFie3.ijcuwwlj96xsl3ll"
    },
    {
      "name": "Herblore: Medicinal",
      "img": "systems/hm3/images/icons/svg/herblore.svg",
      "type": "skill",
      "_id": "soeae3i32wpcl47l",
      "effects": [],
      "folder": null,
      "sort": 0,
      "flags": {},
      "system": {
        "notes": "",
        "description": "",
        "source": "",
        "macros": {
          "type": "script",
          "command": ""
        },
        "type": "Craft",
        "skillBase": {
          "value": "14",
          "formula": "",
          "isFormulaValid": true
        },
        "masteryLevel": "74",
        "effectiveMasteryLevel": 0,
        "ritual": {
          "piety": 0
        },
        "improveFlag": false
      },
      "ownership": {
        "default": 0
      },
      "_stats": {
        "systemId": null,
        "systemVersion": null,
        "coreVersion": null,
        "createdTime": null,
        "modifiedTime": null,
        "lastModifiedBy": null
      },
      "_key": "!actors.items!78QD3CkEWFGwFie3.soeae3i32wpcl47l"
    },
    {
      "img": "systems/hm3/images/icons/svg/herblore.svg",
      "type": "skill",
      "name": "Herblore: Herblore: Poison",
      "_id": "cmwaw8hl2ic9u3hn",
      "effects": [],
      "folder": null,
      "sort": 0,
      "flags": {},
      "system": {
        "notes": "",
        "description": "",
        "source": "",
        "macros": {
          "type": "script",
          "command": ""
        },
        "type": "Craft",
        "skillBase": {
          "value": "14",
          "formula": "",
          "isFormulaValid": true
        },
        "masteryLevel": "74",
        "effectiveMasteryLevel": 0,
        "ritual": {
          "piety": 0
        },
        "improveFlag": false
      },
      "ownership": {
        "default": 0
      },
      "_stats": {
        "systemId": null,
        "systemVersion": null,
        "coreVersion": null,
        "createdTime": null,
        "modifiedTime": null,
        "lastModifiedBy": null
      },
      "_key": "!actors.items!78QD3CkEWFGwFie3.cmwaw8hl2ic9u3hn"
    },
    {
      "name": "Law",
      "type": "skill",
      "img": "systems/hm3/images/icons/svg/law.svg",
      "_id": "v3ite009dxy6tbsu",
      "effects": [],
      "folder": null,
      "sort": 0,
      "flags": {},
      "system": {
        "notes": "",
        "description": "",
        "source": "",
        "macros": {
          "type": "script",
          "command": ""
        },
        "type": "Craft",
        "skillBase": {
          "value": "15",
          "formula": "",
          "isFormulaValid": true
        },
        "masteryLevel": "37",
        "effectiveMasteryLevel": 0,
        "ritual": {
          "piety": 0
        },
        "improveFlag": false
      },
      "ownership": {
        "default": 0
      },
      "_stats": {
        "systemId": null,
        "systemVersion": null,
        "coreVersion": null,
        "createdTime": null,
        "modifiedTime": null,
        "lastModifiedBy": null
      },
      "_key": "!actors.items!78QD3CkEWFGwFie3.v3ite009dxy6tbsu"
    },
    {
      "name": "Lockcraft",
      "img": "systems/hm3/images/icons/svg/lock.svg",
      "type": "skill",
      "_id": "3iixe08zn42cydf9",
      "effects": [],
      "folder": null,
      "sort": 0,
      "flags": {},
      "system": {
        "notes": "",
        "description": "",
        "source": "",
        "macros": {
          "type": "script",
          "command": ""
        },
        "type": "Craft",
        "skillBase": {
          "value": "13",
          "formula": "",
          "isFormulaValid": true
        },
        "masteryLevel": "49",
        "effectiveMasteryLevel": 0,
        "ritual": {
          "piety": 0
        },
        "improveFlag": false
      },
      "ownership": {
        "default": 0
      },
      "_stats": {
        "systemId": null,
        "systemVersion": null,
        "coreVersion": null,
        "createdTime": null,
        "modifiedTime": null,
        "lastModifiedBy": null
      },
      "_key": "!actors.items!78QD3CkEWFGwFie3.3iixe08zn42cydf9"
    },
    {
      "name": "Mathematics",
      "img": "systems/hm3/images/icons/svg/mathematics.svg",
      "type": "skill",
      "_id": "n3tenyyyndnna5d0",
      "effects": [],
      "folder": null,
      "sort": 0,
      "flags": {},
      "system": {
        "notes": "",
        "description": "",
        "source": "",
        "macros": {
          "type": "script",
          "command": ""
        },
        "type": "Craft",
        "skillBase": {
          "value": "16",
          "formula": "",
          "isFormulaValid": true
        },
        "masteryLevel": "36",
        "effectiveMasteryLevel": 0,
        "ritual": {
          "piety": 0
        },
        "improveFlag": false
      },
      "ownership": {
        "default": 0
      },
      "_stats": {
        "systemId": null,
        "systemVersion": null,
        "coreVersion": null,
        "createdTime": null,
        "modifiedTime": null,
        "lastModifiedBy": null
      },
      "_key": "!actors.items!78QD3CkEWFGwFie3.n3tenyyyndnna5d0"
    },
    {
      "type": "skill",
      "img": "systems/hm3/images/icons/svg/caduceus.svg",
      "name": "Physician",
      "_id": "4an62kh3uful5dw6",
      "effects": [],
      "folder": null,
      "sort": 0,
      "flags": {},
      "system": {
        "notes": "",
        "description": "",
        "source": "",
        "macros": {
          "type": "script",
          "command": ""
        },
        "type": "Craft",
        "skillBase": {
          "value": "13",
          "formula": "",
          "isFormulaValid": true
        },
        "masteryLevel": "31",
        "effectiveMasteryLevel": 0,
        "ritual": {
          "piety": 0
        },
        "improveFlag": false
      },
      "ownership": {
        "default": 0
      },
      "_stats": {
        "systemId": null,
        "systemVersion": null,
        "coreVersion": null,
        "createdTime": null,
        "modifiedTime": null,
        "lastModifiedBy": null
      },
      "_key": "!actors.items!78QD3CkEWFGwFie3.4an62kh3uful5dw6"
    },
    {
      "name": "Textilecraft",
      "img": "systems/hm3/images/icons/svg/textilecraft.svg",
      "type": "skill",
      "_id": "cuzeirnzceqza7aj",
      "effects": [],
      "folder": null,
      "sort": 0,
      "flags": {},
      "system": {
        "notes": "",
        "description": "",
        "source": "",
        "macros": {
          "type": "script",
          "command": ""
        },
        "type": "Craft",
        "skillBase": {
          "value": "12",
          "formula": "",
          "isFormulaValid": true
        },
        "masteryLevel": "38",
        "effectiveMasteryLevel": 0,
        "ritual": {
          "piety": 0
        },
        "improveFlag": false
      },
      "ownership": {
        "default": 0
      },
      "_stats": {
        "systemId": null,
        "systemVersion": null,
        "coreVersion": null,
        "createdTime": null,
        "modifiedTime": null,
        "lastModifiedBy": null
      },
      "_key": "!actors.items!78QD3CkEWFGwFie3.cuzeirnzceqza7aj"
    },
    {
      "img": "systems/hm3/images/icons/svg/sack.svg",
      "type": "containergear",
      "name": "Coin purse, leather",
      "_id": "5tfk1fjfeqnq75g4",
      "effects": [],
      "folder": null,
      "sort": 0,
      "flags": {},
      "system": {
        "notes": "",
        "description": "",
        "source": "",
        "macros": {
          "type": "script",
          "command": ""
        },
        "quantity": 1,
        "value": 5,
        "weight": 0.125,
        "isCarried": true,
        "isEquipped": true,
        "container": "on-person",
        "arcane": {
          "isArtifact": false,
          "isAttuned": false,
          "charges": -1,
          "ego": 0
        },
        "capacity": {
          "max": 1,
          "value": 0
        }
      },
      "ownership": {
        "default": 0
      },
      "_stats": {
        "systemId": null,
        "systemVersion": null,
        "coreVersion": null,
        "createdTime": null,
        "modifiedTime": null,
        "lastModifiedBy": null
      },
      "_key": "!actors.items!78QD3CkEWFGwFie3.5tfk1fjfeqnq75g4"
    },
    {
      "img": "systems/hm3/images/icons/svg/dagger.svg",
      "type": "weapongear",
      "name": "Knife",
      "_id": "rpag1aorvehuwcva",
      "effects": [],
      "folder": null,
      "sort": 0,
      "flags": {},
      "system": {
        "notes": "",
        "description": "",
        "source": "",
        "macros": {
          "type": "script",
          "command": ""
        },
        "quantity": 1,
        "value": 6,
        "weight": 1,
        "isCarried": true,
        "isEquipped": true,
        "container": "on-person",
        "arcane": {
          "isArtifact": false,
          "isAttuned": false,
          "charges": -1,
          "ego": 0
        },
        "assocSkill": "Dagger",
        "weaponQuality": 0,
        "attackMasteryLevel": 0,
        "attack": 5,
        "defense": 0,
        "attackModifier": 0,
        "blunt": 0,
        "edged": 1,
        "piercing": 4,
        "defenseMasteryLevel": 0
      },
      "ownership": {
        "default": 0
      },
      "_stats": {
        "systemId": null,
        "systemVersion": null,
        "coreVersion": null,
        "createdTime": null,
        "modifiedTime": null,
        "lastModifiedBy": null
      },
      "_key": "!actors.items!78QD3CkEWFGwFie3.rpag1aorvehuwcva"
    },
    {
      "name": "Leortevald",
      "img": "systems/hm3/images/icons/svg/miscgear.svg",
      "type": "miscgear",
      "_id": "5ward6d6w4o7ra0k",
      "effects": [],
      "folder": null,
      "sort": 0,
      "flags": {},
      "system": {
        "notes": "Poison",
        "description": "",
        "source": "",
        "macros": {
          "type": "script",
          "command": ""
        },
        "quantity": 14,
        "value": 0,
        "weight": 1,
        "isCarried": true,
        "isEquipped": true,
        "container": "on-person",
        "arcane": {
          "isArtifact": false,
          "isAttuned": false,
          "charges": -1,
          "ego": 0
        }
      },
      "ownership": {
        "default": 0
      },
      "_stats": {
        "systemId": null,
        "systemVersion": null,
        "coreVersion": null,
        "createdTime": null,
        "modifiedTime": null,
        "lastModifiedBy": null
      },
      "_key": "!actors.items!78QD3CkEWFGwFie3.5ward6d6w4o7ra0k"
    },
    {
      "type": "miscgear",
      "img": "systems/hm3/images/icons/svg/miscgear.svg",
      "name": "Gaethipa",
      "_id": "pmmrrq67kzdeba0z",
      "effects": [],
      "folder": null,
      "sort": 0,
      "flags": {},
      "system": {
        "notes": "Poison",
        "description": "",
        "source": "",
        "macros": {
          "type": "script",
          "command": ""
        },
        "quantity": 12,
        "value": 0,
        "weight": 1,
        "isCarried": true,
        "isEquipped": true,
        "container": "on-person",
        "arcane": {
          "isArtifact": false,
          "isAttuned": false,
          "charges": -1,
          "ego": 0
        }
      },
      "ownership": {
        "default": 0
      },
      "_stats": {
        "systemId": null,
        "systemVersion": null,
        "coreVersion": null,
        "createdTime": null,
        "modifiedTime": null,
        "lastModifiedBy": null
      },
      "_key": "!actors.items!78QD3CkEWFGwFie3.pmmrrq67kzdeba0z"
    },
    {
      "name": "Yulpris",
      "type": "miscgear",
      "img": "systems/hm3/images/icons/svg/miscgear.svg",
      "_id": "txar4ge6fdaosarw",
      "effects": [],
      "folder": null,
      "sort": 0,
      "flags": {},
      "system": {
        "notes": "Antidote",
        "description": "",
        "source": "",
        "macros": {
          "type": "script",
          "command": ""
        },
        "quantity": 6,
        "value": 0,
        "weight": 1,
        "isCarried": true,
        "isEquipped": true,
        "container": "on-person",
        "arcane": {
          "isArtifact": false,
          "isAttuned": false,
          "charges": -1,
          "ego": 0
        }
      },
      "ownership": {
        "default": 0
      },
      "_stats": {
        "systemId": null,
        "systemVersion": null,
        "coreVersion": null,
        "createdTime": null,
        "modifiedTime": null,
        "lastModifiedBy": null
      },
      "_key": "!actors.items!78QD3CkEWFGwFie3.txar4ge6fdaosarw"
    },
    {
      "img": "systems/hm3/images/icons/svg/miscgear.svg",
      "type": "miscgear",
      "name": "Wool Scarf",
      "_id": "us9tjj5uoook949y",
      "effects": [],
      "folder": null,
      "sort": 0,
      "flags": {},
      "system": {
        "notes": "",
        "description": "",
        "source": "",
        "macros": {
          "type": "script",
          "command": ""
        },
        "quantity": 1,
        "value": 0,
        "weight": 1,
        "isCarried": true,
        "isEquipped": true,
        "container": "on-person",
        "arcane": {
          "isArtifact": false,
          "isAttuned": false,
          "charges": -1,
          "ego": 0
        }
      },
      "ownership": {
        "default": 0
      },
      "_stats": {
        "systemId": null,
        "systemVersion": null,
        "coreVersion": null,
        "createdTime": null,
        "modifiedTime": null,
        "lastModifiedBy": null
      },
      "_key": "!actors.items!78QD3CkEWFGwFie3.us9tjj5uoook949y"
    },
    {
      "name": "Worsted Tunic",
      "img": "systems/hm3/images/icons/svg/tunic.svg",
      "type": "armorgear",
      "_id": "mqmizq51tn0n49fm",
      "effects": [],
      "folder": null,
      "sort": 0,
      "flags": {},
      "system": {
        "notes": "",
        "description": "",
        "source": "",
        "macros": {
          "type": "script",
          "command": ""
        },
        "quantity": 1,
        "value": 269,
        "weight": 4.4,
        "isCarried": true,
        "isEquipped": true,
        "container": "on-person",
        "arcane": {
          "isArtifact": false,
          "isAttuned": false,
          "charges": -1,
          "ego": 0
        },
        "material": "Cloth",
        "armorQuality": 0,
        "locations": [
          "Upper Arm",
          "Shoulder",
          "Thorax",
          "Abdomen",
          "Hip",
          "Groin"
        ],
        "protection": {
          "blunt": 1,
          "edged": 1,
          "piercing": 1,
          "fire": 1
        },
        "size": 6
      },
      "ownership": {
        "default": 0
      },
      "_stats": {
        "systemId": null,
        "systemVersion": null,
        "coreVersion": null,
        "createdTime": null,
        "modifiedTime": null,
        "lastModifiedBy": null
      },
      "_key": "!actors.items!78QD3CkEWFGwFie3.mqmizq51tn0n49fm"
    },
    {
      "name": "Worsted Leggings",
      "img": "systems/hm3/images/icons/svg/legging.svg",
      "type": "armorgear",
      "_id": "9i4f2joz2mb001ix",
      "effects": [],
      "folder": null,
      "sort": 0,
      "flags": {},
      "system": {
        "notes": "",
        "description": "",
        "source": "",
        "macros": {
          "type": "script",
          "command": ""
        },
        "quantity": 1,
        "value": 88,
        "weight": 4.4,
        "isCarried": true,
        "isEquipped": true,
        "container": "on-person",
        "arcane": {
          "isArtifact": false,
          "isAttuned": false,
          "charges": -1,
          "ego": 0
        },
        "material": "Cloth",
        "armorQuality": 0,
        "locations": [
          "Hip",
          "Groin",
          "Thigh",
          "Knee",
          "Calf",
          "Foot"
        ],
        "protection": {
          "blunt": 1,
          "edged": 1,
          "piercing": 1,
          "fire": 1
        },
        "size": 6
      },
      "ownership": {
        "default": 0
      },
      "_stats": {
        "systemId": null,
        "systemVersion": null,
        "coreVersion": null,
        "createdTime": null,
        "modifiedTime": null,
        "lastModifiedBy": null
      },
      "_key": "!actors.items!78QD3CkEWFGwFie3.9i4f2joz2mb001ix"
    },
    {
      "type": "armorgear",
      "img": "systems/hm3/images/icons/svg/shoe.svg",
      "name": "Leather Shoes",
      "_id": "er8nd2cid0us481q",
      "effects": [],
      "folder": null,
      "sort": 0,
      "flags": {},
      "system": {
        "notes": "",
        "description": "",
        "source": "",
        "macros": {
          "type": "script",
          "command": ""
        },
        "quantity": 1,
        "value": 24,
        "weight": 1.2,
        "isCarried": true,
        "isEquipped": true,
        "container": "on-person",
        "arcane": {
          "isArtifact": false,
          "isAttuned": false,
          "charges": -1,
          "ego": 0
        },
        "material": "Leather",
        "armorQuality": 0,
        "locations": [
          "Foot"
        ],
        "protection": {
          "blunt": 2,
          "edged": 4,
          "piercing": 3,
          "fire": 3
        },
        "size": 6
      },
      "ownership": {
        "default": 0
      },
      "_stats": {
        "systemId": null,
        "systemVersion": null,
        "coreVersion": null,
        "createdTime": null,
        "modifiedTime": null,
        "lastModifiedBy": null
      },
      "_key": "!actors.items!78QD3CkEWFGwFie3.er8nd2cid0us481q"
    },
    {
      "img": "systems/hm3/images/icons/png/peoni.png",
      "type": "invocation",
      "name": "Baptism",
      "_id": "rgd9es59fxs1z7sb",
      "effects": [],
      "folder": null,
      "sort": 0,
      "flags": {},
      "system": {
        "notes": "",
        "description": "",
        "source": "",
        "macros": {
          "type": "script",
          "command": ""
        },
        "diety": "Peoni",
        "circle": 2,
        "effectiveMasteryLevel": 0
      },
      "ownership": {
        "default": 0
      },
      "_stats": {
        "systemId": null,
        "systemVersion": null,
        "coreVersion": null,
        "createdTime": null,
        "modifiedTime": null,
        "lastModifiedBy": null
      },
      "_key": "!actors.items!78QD3CkEWFGwFie3.rgd9es59fxs1z7sb"
    },
    {
      "name": "Blessing",
      "img": "systems/hm3/images/icons/png/peoni.png",
      "type": "invocation",
      "_id": "ga1m6r5ivli68bwm",
      "effects": [],
      "folder": null,
      "sort": 0,
      "flags": {},
      "system": {
        "notes": "",
        "description": "",
        "source": "",
        "macros": {
          "type": "script",
          "command": ""
        },
        "diety": "Peoni",
        "circle": 2,
        "effectiveMasteryLevel": 0
      },
      "ownership": {
        "default": 0
      },
      "_stats": {
        "systemId": null,
        "systemVersion": null,
        "coreVersion": null,
        "createdTime": null,
        "modifiedTime": null,
        "lastModifiedBy": null
      },
      "_key": "!actors.items!78QD3CkEWFGwFie3.ga1m6r5ivli68bwm"
    },
    {
      "img": "systems/hm3/images/icons/png/peoni.png",
      "type": "invocation",
      "name": "Commune",
      "_id": "24tgvwj5e7uqh2wl",
      "effects": [],
      "folder": null,
      "sort": 0,
      "flags": {},
      "system": {
        "notes": "",
        "description": "",
        "source": "",
        "macros": {
          "type": "script",
          "command": ""
        },
        "diety": "Peoni",
        "circle": 2,
        "effectiveMasteryLevel": 0
      },
      "ownership": {
        "default": 0
      },
      "_stats": {
        "systemId": null,
        "systemVersion": null,
        "coreVersion": null,
        "createdTime": null,
        "modifiedTime": null,
        "lastModifiedBy": null
      },
      "_key": "!actors.items!78QD3CkEWFGwFie3.24tgvwj5e7uqh2wl"
    },
    {
      "type": "invocation",
      "img": "systems/hm3/images/icons/png/peoni.png",
      "name": "Liturgy",
      "_id": "angepaknhylhx3ov",
      "effects": [],
      "folder": null,
      "sort": 0,
      "flags": {},
      "system": {
        "notes": "",
        "description": "",
        "source": "",
        "macros": {
          "type": "script",
          "command": ""
        },
        "diety": "Peoni",
        "circle": 2,
        "effectiveMasteryLevel": 0
      },
      "ownership": {
        "default": 0
      },
      "_stats": {
        "systemId": null,
        "systemVersion": null,
        "coreVersion": null,
        "createdTime": null,
        "modifiedTime": null,
        "lastModifiedBy": null
      },
      "_key": "!actors.items!78QD3CkEWFGwFie3.angepaknhylhx3ov"
    },
    {
      "type": "invocation",
      "img": "systems/hm3/images/icons/png/peoni.png",
      "name": "Marriage",
      "_id": "bviarye4rwwk6xl4",
      "effects": [],
      "folder": null,
      "sort": 0,
      "flags": {},
      "system": {
        "notes": "",
        "description": "",
        "source": "",
        "macros": {
          "type": "script",
          "command": ""
        },
        "diety": "Peoni",
        "circle": 2,
        "effectiveMasteryLevel": 0
      },
      "ownership": {
        "default": 0
      },
      "_stats": {
        "systemId": null,
        "systemVersion": null,
        "coreVersion": null,
        "createdTime": null,
        "modifiedTime": null,
        "lastModifiedBy": null
      },
      "_key": "!actors.items!78QD3CkEWFGwFie3.bviarye4rwwk6xl4"
    },
    {
      "name": "Passage of the Soul",
      "type": "invocation",
      "img": "systems/hm3/images/icons/png/peoni.png",
      "_id": "imeish9bge8jqzpy",
      "effects": [],
      "folder": null,
      "sort": 0,
      "flags": {},
      "system": {
        "notes": "",
        "description": "",
        "source": "",
        "macros": {
          "type": "script",
          "command": ""
        },
        "diety": "Peoni",
        "circle": 2,
        "effectiveMasteryLevel": 0
      },
      "ownership": {
        "default": 0
      },
      "_stats": {
        "systemId": null,
        "systemVersion": null,
        "coreVersion": null,
        "createdTime": null,
        "modifiedTime": null,
        "lastModifiedBy": null
      },
      "_key": "!actors.items!78QD3CkEWFGwFie3.imeish9bge8jqzpy"
    },
    {
      "name": "Dekejis’ Gift",
      "img": "systems/hm3/images/icons/png/peoni.png",
      "type": "invocation",
      "_id": "9wvxvd8iltb1wvor",
      "effects": [],
      "folder": null,
      "sort": 0,
      "flags": {},
      "system": {
        "notes": "",
        "description": "",
        "source": "",
        "macros": {
          "type": "script",
          "command": ""
        },
        "diety": "Peoni",
        "circle": 2,
        "effectiveMasteryLevel": 0
      },
      "ownership": {
        "default": 0
      },
      "_stats": {
        "systemId": null,
        "systemVersion": null,
        "coreVersion": null,
        "createdTime": null,
        "modifiedTime": null,
        "lastModifiedBy": null
      },
      "_key": "!actors.items!78QD3CkEWFGwFie3.9wvxvd8iltb1wvor"
    },
    {
      "img": "systems/hm3/images/icons/png/peoni.png",
      "type": "invocation",
      "name": "Vesha’s Tale",
      "_id": "okhe94efrufkoqbz",
      "effects": [],
      "folder": null,
      "sort": 0,
      "flags": {},
      "system": {
        "notes": "",
        "description": "",
        "source": "",
        "macros": {
          "type": "script",
          "command": ""
        },
        "diety": "Peoni",
        "circle": 2,
        "effectiveMasteryLevel": 0
      },
      "ownership": {
        "default": 0
      },
      "_stats": {
        "systemId": null,
        "systemVersion": null,
        "coreVersion": null,
        "createdTime": null,
        "modifiedTime": null,
        "lastModifiedBy": null
      },
      "_key": "!actors.items!78QD3CkEWFGwFie3.okhe94efrufkoqbz"
    },
    {
      "type": "invocation",
      "img": "systems/hm3/images/icons/png/peoni.png",
      "name": "Eyes of Dekjis",
      "_id": "vkm9uq92t2cqr0q4",
      "effects": [],
      "folder": null,
      "sort": 0,
      "flags": {},
      "system": {
        "notes": "",
        "description": "",
        "source": "",
        "macros": {
          "type": "script",
          "command": ""
        },
        "diety": "Peoni",
        "circle": 3,
        "effectiveMasteryLevel": 0
      },
      "ownership": {
        "default": 0
      },
      "_stats": {
        "systemId": null,
        "systemVersion": null,
        "coreVersion": null,
        "createdTime": null,
        "modifiedTime": null,
        "lastModifiedBy": null
      },
      "_key": "!actors.items!78QD3CkEWFGwFie3.vkm9uq92t2cqr0q4"
    },
    {
      "type": "invocation",
      "img": "systems/hm3/images/icons/png/peoni.png",
      "name": "House in Kamil",
      "_id": "6t5ku4664hv5bb86",
      "effects": [],
      "folder": null,
      "sort": 0,
      "flags": {},
      "system": {
        "notes": "",
        "description": "",
        "source": "",
        "macros": {
          "type": "script",
          "command": ""
        },
        "diety": "Peoni",
        "circle": 3,
        "effectiveMasteryLevel": 0
      },
      "ownership": {
        "default": 0
      },
      "_stats": {
        "systemId": null,
        "systemVersion": null,
        "coreVersion": null,
        "createdTime": null,
        "modifiedTime": null,
        "lastModifiedBy": null
      },
      "_key": "!actors.items!78QD3CkEWFGwFie3.6t5ku4664hv5bb86"
    },
    {
      "name": "Krasula’s Whisper",
      "img": "systems/hm3/images/icons/png/peoni.png",
      "type": "invocation",
      "_id": "uj9g6l4tdghhsfvr",
      "effects": [],
      "folder": null,
      "sort": 0,
      "flags": {},
      "system": {
        "notes": "",
        "description": "",
        "source": "",
        "macros": {
          "type": "script",
          "command": ""
        },
        "diety": "Peoni",
        "circle": 3,
        "effectiveMasteryLevel": 0
      },
      "ownership": {
        "default": 0
      },
      "_stats": {
        "systemId": null,
        "systemVersion": null,
        "coreVersion": null,
        "createdTime": null,
        "modifiedTime": null,
        "lastModifiedBy": null
      },
      "_key": "!actors.items!78QD3CkEWFGwFie3.uj9g6l4tdghhsfvr"
    },
    {
      "type": "invocation",
      "img": "systems/hm3/images/icons/png/peoni.png",
      "name": "Vesha’s Sense",
      "_id": "5bq8yfhey5pq2w3z",
      "effects": [],
      "folder": null,
      "sort": 0,
      "flags": {},
      "system": {
        "notes": "",
        "description": "",
        "source": "",
        "macros": {
          "type": "script",
          "command": ""
        },
        "diety": "Peoni",
        "circle": 3,
        "effectiveMasteryLevel": 0
      },
      "ownership": {
        "default": 0
      },
      "_stats": {
        "systemId": null,
        "systemVersion": null,
        "coreVersion": null,
        "createdTime": null,
        "modifiedTime": null,
        "lastModifiedBy": null
      },
      "_key": "!actors.items!78QD3CkEWFGwFie3.5bq8yfhey5pq2w3z"
    },
    {
      "name": "Skull",
      "type": "armorlocation",
      "_id": "341xwf8o0er9cqu7",
      "img": "icons/svg/item-bag.svg",
      "effects": [],
      "folder": null,
      "sort": 0,
      "flags": {},
      "system": {
        "layers": "",
        "armorQuality": 0,
        "blunt": 0,
        "edged": 0,
        "piercing": 0,
        "fire": 0,
        "isFumble": false,
        "isStumble": false,
        "isAmputate": false,
        "impactType": "skull",
        "effectiveImpact": {
          "ei1": "M1",
          "ei5": "S2",
          "ei9": "S3",
          "ei13": "K4",
          "ei17": "K5"
        },
        "probWeight": {
          "high": 150,
          "mid": 50,
          "low": 0
        }
      },
      "ownership": {
        "default": 0
      },
      "_stats": {
        "systemId": null,
        "systemVersion": null,
        "coreVersion": null,
        "createdTime": null,
        "modifiedTime": null,
        "lastModifiedBy": null
      },
      "_key": "!actors.items!78QD3CkEWFGwFie3.341xwf8o0er9cqu7"
    },
    {
      "type": "armorlocation",
      "name": "Face",
      "_id": "0qyivciv0p0q8s59",
      "img": "icons/svg/item-bag.svg",
      "effects": [],
      "folder": null,
      "sort": 0,
      "flags": {},
      "system": {
        "layers": "",
        "armorQuality": 0,
        "blunt": 0,
        "edged": 0,
        "piercing": 0,
        "fire": 0,
        "isFumble": false,
        "isStumble": false,
        "isAmputate": false,
        "impactType": "face",
        "effectiveImpact": {
          "ei1": "M1",
          "ei5": "S2",
          "ei9": "S3",
          "ei13": "G4",
          "ei17": "K5"
        },
        "probWeight": {
          "high": 150,
          "mid": 50,
          "low": 0
        }
      },
      "ownership": {
        "default": 0
      },
      "_stats": {
        "systemId": null,
        "systemVersion": null,
        "coreVersion": null,
        "createdTime": null,
        "modifiedTime": null,
        "lastModifiedBy": null
      },
      "_key": "!actors.items!78QD3CkEWFGwFie3.0qyivciv0p0q8s59"
    },
    {
      "name": "Neck",
      "type": "armorlocation",
      "_id": "o4kmqbd9ycasi9q0",
      "img": "icons/svg/item-bag.svg",
      "effects": [],
      "folder": null,
      "sort": 0,
      "flags": {},
      "system": {
        "layers": "",
        "armorQuality": 0,
        "blunt": 0,
        "edged": 0,
        "piercing": 0,
        "fire": 0,
        "isFumble": false,
        "isStumble": false,
        "isAmputate": true,
        "impactType": "neck",
        "effectiveImpact": {
          "ei1": "M1",
          "ei5": "S2",
          "ei9": "S3",
          "ei13": "K4",
          "ei17": "K5"
        },
        "probWeight": {
          "high": 150,
          "mid": 50,
          "low": 0
        }
      },
      "ownership": {
        "default": 0
      },
      "_stats": {
        "systemId": null,
        "systemVersion": null,
        "coreVersion": null,
        "createdTime": null,
        "modifiedTime": null,
        "lastModifiedBy": null
      },
      "_key": "!actors.items!78QD3CkEWFGwFie3.o4kmqbd9ycasi9q0"
    },
    {
      "type": "armorlocation",
      "name": "Left Shoulder",
      "_id": "ausc9bzmuu5titsl",
      "img": "icons/svg/item-bag.svg",
      "effects": [],
      "folder": null,
      "sort": 0,
      "flags": {},
      "system": {
        "layers": "",
        "armorQuality": 0,
        "blunt": 0,
        "edged": 0,
        "piercing": 0,
        "fire": 0,
        "isFumble": true,
        "isStumble": false,
        "isAmputate": false,
        "impactType": "shoulder",
        "effectiveImpact": {
          "ei1": "M1",
          "ei5": "S2",
          "ei9": "S3",
          "ei13": "G4",
          "ei17": "K4"
        },
        "probWeight": {
          "high": 60,
          "mid": 60,
          "low": 0
        }
      },
      "ownership": {
        "default": 0
      },
      "_stats": {
        "systemId": null,
        "systemVersion": null,
        "coreVersion": null,
        "createdTime": null,
        "modifiedTime": null,
        "lastModifiedBy": null
      },
      "_key": "!actors.items!78QD3CkEWFGwFie3.ausc9bzmuu5titsl"
    },
    {
      "name": "Right Shoulder",
      "type": "armorlocation",
      "_id": "rxce0jkhehk84hmz",
      "img": "icons/svg/item-bag.svg",
      "effects": [],
      "folder": null,
      "sort": 0,
      "flags": {},
      "system": {
        "layers": "",
        "armorQuality": 0,
        "blunt": 0,
        "edged": 0,
        "piercing": 0,
        "fire": 0,
        "isFumble": true,
        "isStumble": false,
        "isAmputate": false,
        "impactType": "shoulder",
        "effectiveImpact": {
          "ei1": "M1",
          "ei5": "S2",
          "ei9": "S3",
          "ei13": "G4",
          "ei17": "K4"
        },
        "probWeight": {
          "high": 60,
          "mid": 60,
          "low": 0
        }
      },
      "ownership": {
        "default": 0
      },
      "_stats": {
        "systemId": null,
        "systemVersion": null,
        "coreVersion": null,
        "createdTime": null,
        "modifiedTime": null,
        "lastModifiedBy": null
      },
      "_key": "!actors.items!78QD3CkEWFGwFie3.rxce0jkhehk84hmz"
    },
    {
      "type": "armorlocation",
      "name": "Left Upper Arm",
      "_id": "f0c7jnw0medwvtb5",
      "img": "icons/svg/item-bag.svg",
      "effects": [],
      "folder": null,
      "sort": 0,
      "flags": {},
      "system": {
        "layers": "",
        "armorQuality": 0,
        "blunt": 0,
        "edged": 0,
        "piercing": 0,
        "fire": 0,
        "isFumble": true,
        "isStumble": false,
        "isAmputate": true,
        "impactType": "upperarm",
        "effectiveImpact": {
          "ei1": "M1",
          "ei5": "M1",
          "ei9": "S2",
          "ei13": "S3",
          "ei17": "G4"
        },
        "probWeight": {
          "high": 60,
          "mid": 30,
          "low": 0
        }
      },
      "ownership": {
        "default": 0
      },
      "_stats": {
        "systemId": null,
        "systemVersion": null,
        "coreVersion": null,
        "createdTime": null,
        "modifiedTime": null,
        "lastModifiedBy": null
      },
      "_key": "!actors.items!78QD3CkEWFGwFie3.f0c7jnw0medwvtb5"
    },
    {
      "type": "armorlocation",
      "name": "Right Upper Arm",
      "_id": "235tz6es1y1dpmiu",
      "img": "icons/svg/item-bag.svg",
      "effects": [],
      "folder": null,
      "sort": 0,
      "flags": {},
      "system": {
        "layers": "",
        "armorQuality": 0,
        "blunt": 0,
        "edged": 0,
        "piercing": 0,
        "fire": 0,
        "isFumble": true,
        "isStumble": false,
        "isAmputate": true,
        "impactType": "upperarm",
        "effectiveImpact": {
          "ei1": "M1",
          "ei5": "M1",
          "ei9": "S2",
          "ei13": "S3",
          "ei17": "G4"
        },
        "probWeight": {
          "high": 60,
          "mid": 30,
          "low": 0
        }
      },
      "ownership": {
        "default": 0
      },
      "_stats": {
        "systemId": null,
        "systemVersion": null,
        "coreVersion": null,
        "createdTime": null,
        "modifiedTime": null,
        "lastModifiedBy": null
      },
      "_key": "!actors.items!78QD3CkEWFGwFie3.235tz6es1y1dpmiu"
    },
    {
      "name": "Left Elbow",
      "type": "armorlocation",
      "_id": "6d0ilwtsv1dok9jq",
      "img": "icons/svg/item-bag.svg",
      "effects": [],
      "folder": null,
      "sort": 0,
      "flags": {},
      "system": {
        "layers": "",
        "armorQuality": 0,
        "blunt": 0,
        "edged": 0,
        "piercing": 0,
        "fire": 0,
        "isFumble": true,
        "isStumble": false,
        "isAmputate": true,
        "impactType": "elbow",
        "effectiveImpact": {
          "ei1": "M1",
          "ei5": "S2",
          "ei9": "S3",
          "ei13": "G4",
          "ei17": "G5"
        },
        "probWeight": {
          "high": 20,
          "mid": 10,
          "low": 0
        }
      },
      "ownership": {
        "default": 0
      },
      "_stats": {
        "systemId": null,
        "systemVersion": null,
        "coreVersion": null,
        "createdTime": null,
        "modifiedTime": null,
        "lastModifiedBy": null
      },
      "_key": "!actors.items!78QD3CkEWFGwFie3.6d0ilwtsv1dok9jq"
    },
    {
      "name": "Right Elbow",
      "type": "armorlocation",
      "_id": "nk3r4jmw5cs5zhe0",
      "img": "icons/svg/item-bag.svg",
      "effects": [],
      "folder": null,
      "sort": 0,
      "flags": {},
      "system": {
        "layers": "",
        "armorQuality": 0,
        "blunt": 0,
        "edged": 0,
        "piercing": 0,
        "fire": 0,
        "isFumble": true,
        "isStumble": false,
        "isAmputate": true,
        "impactType": "elbow",
        "effectiveImpact": {
          "ei1": "M1",
          "ei5": "S2",
          "ei9": "S3",
          "ei13": "G4",
          "ei17": "G5"
        },
        "probWeight": {
          "high": 20,
          "mid": 10,
          "low": 0
        }
      },
      "ownership": {
        "default": 0
      },
      "_stats": {
        "systemId": null,
        "systemVersion": null,
        "coreVersion": null,
        "createdTime": null,
        "modifiedTime": null,
        "lastModifiedBy": null
      },
      "_key": "!actors.items!78QD3CkEWFGwFie3.nk3r4jmw5cs5zhe0"
    },
    {
      "name": "Left Hand",
      "type": "armorlocation",
      "_id": "qrrsev288ol158xx",
      "img": "icons/svg/item-bag.svg",
      "effects": [],
      "folder": null,
      "sort": 0,
      "flags": {},
      "system": {
        "layers": "",
        "armorQuality": 0,
        "blunt": 0,
        "edged": 0,
        "piercing": 0,
        "fire": 0,
        "isFumble": true,
        "isStumble": false,
        "isAmputate": true,
        "impactType": "hand",
        "effectiveImpact": {
          "ei1": "M1",
          "ei5": "S2",
          "ei9": "S3",
          "ei13": "G4",
          "ei17": "G5"
        },
        "probWeight": {
          "high": 20,
          "mid": 20,
          "low": 30
        }
      },
      "ownership": {
        "default": 0
      },
      "_stats": {
        "systemId": null,
        "systemVersion": null,
        "coreVersion": null,
        "createdTime": null,
        "modifiedTime": null,
        "lastModifiedBy": null
      },
      "_key": "!actors.items!78QD3CkEWFGwFie3.qrrsev288ol158xx"
    },
    {
      "type": "armorlocation",
      "name": "Right Hand",
      "_id": "zayhk3w8wbah4qei",
      "img": "icons/svg/item-bag.svg",
      "effects": [],
      "folder": null,
      "sort": 0,
      "flags": {},
      "system": {
        "layers": "",
        "armorQuality": 0,
        "blunt": 0,
        "edged": 0,
        "piercing": 0,
        "fire": 0,
        "isFumble": true,
        "isStumble": false,
        "isAmputate": true,
        "impactType": "hand",
        "effectiveImpact": {
          "ei1": "M1",
          "ei5": "S2",
          "ei9": "S3",
          "ei13": "G4",
          "ei17": "G5"
        },
        "probWeight": {
          "high": 20,
          "mid": 20,
          "low": 30
        }
      },
      "ownership": {
        "default": 0
      },
      "_stats": {
        "systemId": null,
        "systemVersion": null,
        "coreVersion": null,
        "createdTime": null,
        "modifiedTime": null,
        "lastModifiedBy": null
      },
      "_key": "!actors.items!78QD3CkEWFGwFie3.zayhk3w8wbah4qei"
    },
    {
      "type": "armorlocation",
      "name": "Thorax",
      "_id": "zy5slydtn6agv9hu",
      "img": "icons/svg/item-bag.svg",
      "effects": [],
      "folder": null,
      "sort": 0,
      "flags": {},
      "system": {
        "layers": "",
        "armorQuality": 0,
        "blunt": 0,
        "edged": 0,
        "piercing": 0,
        "fire": 0,
        "isFumble": false,
        "isStumble": false,
        "isAmputate": false,
        "impactType": "thorax",
        "effectiveImpact": {
          "ei1": "M1",
          "ei5": "S2",
          "ei9": "S3",
          "ei13": "G4",
          "ei17": "K5"
        },
        "probWeight": {
          "high": 100,
          "mid": 170,
          "low": 70
        }
      },
      "ownership": {
        "default": 0
      },
      "_stats": {
        "systemId": null,
        "systemVersion": null,
        "coreVersion": null,
        "createdTime": null,
        "modifiedTime": null,
        "lastModifiedBy": null
      },
      "_key": "!actors.items!78QD3CkEWFGwFie3.zy5slydtn6agv9hu"
    },
    {
      "name": "Abdomen",
      "type": "armorlocation",
      "_id": "6l3rig9viewtzyib",
      "img": "icons/svg/item-bag.svg",
      "effects": [],
      "folder": null,
      "sort": 0,
      "flags": {},
      "system": {
        "layers": "",
        "armorQuality": 0,
        "blunt": 0,
        "edged": 0,
        "piercing": 0,
        "fire": 0,
        "isFumble": false,
        "isStumble": false,
        "isAmputate": false,
        "impactType": "abdomen",
        "effectiveImpact": {
          "ei1": "M1",
          "ei5": "S2",
          "ei9": "S3",
          "ei13": "K4",
          "ei17": "K5"
        },
        "probWeight": {
          "high": 60,
          "mid": 100,
          "low": 100
        }
      },
      "ownership": {
        "default": 0
      },
      "_stats": {
        "systemId": null,
        "systemVersion": null,
        "coreVersion": null,
        "createdTime": null,
        "modifiedTime": null,
        "lastModifiedBy": null
      },
      "_key": "!actors.items!78QD3CkEWFGwFie3.6l3rig9viewtzyib"
    },
    {
      "type": "armorlocation",
      "name": "Groin",
      "_id": "4miu6lg0xfnbcpw5",
      "img": "icons/svg/item-bag.svg",
      "effects": [],
      "folder": null,
      "sort": 0,
      "flags": {},
      "system": {
        "layers": "",
        "armorQuality": 0,
        "blunt": 0,
        "edged": 0,
        "piercing": 0,
        "fire": 0,
        "isFumble": false,
        "isStumble": false,
        "isAmputate": true,
        "impactType": "groin",
        "effectiveImpact": {
          "ei1": "M1",
          "ei5": "S2",
          "ei9": "S3",
          "ei13": "G4",
          "ei17": "G5"
        },
        "probWeight": {
          "high": 0,
          "mid": 40,
          "low": 60
        }
      },
      "ownership": {
        "default": 0
      },
      "_stats": {
        "systemId": null,
        "systemVersion": null,
        "coreVersion": null,
        "createdTime": null,
        "modifiedTime": null,
        "lastModifiedBy": null
      },
      "_key": "!actors.items!78QD3CkEWFGwFie3.4miu6lg0xfnbcpw5"
    },
    {
      "type": "armorlocation",
      "name": "Left Hip",
      "_id": "4oux37ge83rd5s8s",
      "img": "icons/svg/item-bag.svg",
      "effects": [],
      "folder": null,
      "sort": 0,
      "flags": {},
      "system": {
        "layers": "",
        "armorQuality": 0,
        "blunt": 0,
        "edged": 0,
        "piercing": 0,
        "fire": 0,
        "isFumble": false,
        "isStumble": true,
        "isAmputate": false,
        "impactType": "hip",
        "effectiveImpact": {
          "ei1": "M1",
          "ei5": "S2",
          "ei9": "S3",
          "ei13": "G4",
          "ei17": "K4"
        },
        "probWeight": {
          "high": 0,
          "mid": 30,
          "low": 70
        }
      },
      "ownership": {
        "default": 0
      },
      "_stats": {
        "systemId": null,
        "systemVersion": null,
        "coreVersion": null,
        "createdTime": null,
        "modifiedTime": null,
        "lastModifiedBy": null
      },
      "_key": "!actors.items!78QD3CkEWFGwFie3.4oux37ge83rd5s8s"
    },
    {
      "type": "armorlocation",
      "name": "Right Hip",
      "_id": "fs53a10tnypcuct4",
      "img": "icons/svg/item-bag.svg",
      "effects": [],
      "folder": null,
      "sort": 0,
      "flags": {},
      "system": {
        "layers": "",
        "armorQuality": 0,
        "blunt": 0,
        "edged": 0,
        "piercing": 0,
        "fire": 0,
        "isFumble": false,
        "isStumble": true,
        "isAmputate": false,
        "impactType": "hip",
        "effectiveImpact": {
          "ei1": "M1",
          "ei5": "S2",
          "ei9": "S3",
          "ei13": "G4",
          "ei17": "K4"
        },
        "probWeight": {
          "high": 0,
          "mid": 30,
          "low": 70
        }
      },
      "ownership": {
        "default": 0
      },
      "_stats": {
        "systemId": null,
        "systemVersion": null,
        "coreVersion": null,
        "createdTime": null,
        "modifiedTime": null,
        "lastModifiedBy": null
      },
      "_key": "!actors.items!78QD3CkEWFGwFie3.fs53a10tnypcuct4"
    },
    {
      "name": "Left Thigh",
      "type": "armorlocation",
      "_id": "p6zfvtkkrjo6gnkf",
      "img": "icons/svg/item-bag.svg",
      "effects": [],
      "folder": null,
      "sort": 0,
      "flags": {},
      "system": {
        "layers": "",
        "armorQuality": 0,
        "blunt": 0,
        "edged": 0,
        "piercing": 0,
        "fire": 0,
        "isFumble": false,
        "isStumble": true,
        "isAmputate": true,
        "impactType": "thigh",
        "effectiveImpact": {
          "ei1": "M1",
          "ei5": "S2",
          "ei9": "S3",
          "ei13": "G4",
          "ei17": "K4"
        },
        "probWeight": {
          "high": 0,
          "mid": 40,
          "low": 100
        }
      },
      "ownership": {
        "default": 0
      },
      "_stats": {
        "systemId": null,
        "systemVersion": null,
        "coreVersion": null,
        "createdTime": null,
        "modifiedTime": null,
        "lastModifiedBy": null
      },
      "_key": "!actors.items!78QD3CkEWFGwFie3.p6zfvtkkrjo6gnkf"
    },
    {
      "type": "armorlocation",
      "name": "Right Thigh",
      "_id": "15ux3qqeomap6arv",
      "img": "icons/svg/item-bag.svg",
      "effects": [],
      "folder": null,
      "sort": 0,
      "flags": {},
      "system": {
        "layers": "",
        "armorQuality": 0,
        "blunt": 0,
        "edged": 0,
        "piercing": 0,
        "fire": 0,
        "isFumble": false,
        "isStumble": true,
        "isAmputate": true,
        "impactType": "thigh",
        "effectiveImpact": {
          "ei1": "M1",
          "ei5": "S2",
          "ei9": "S3",
          "ei13": "G4",
          "ei17": "K4"
        },
        "probWeight": {
          "high": 0,
          "mid": 40,
          "low": 100
        }
      },
      "ownership": {
        "default": 0
      },
      "_stats": {
        "systemId": null,
        "systemVersion": null,
        "coreVersion": null,
        "createdTime": null,
        "modifiedTime": null,
        "lastModifiedBy": null
      },
      "_key": "!actors.items!78QD3CkEWFGwFie3.15ux3qqeomap6arv"
    },
    {
      "name": "Left Knee",
      "type": "armorlocation",
      "_id": "cl22to1qg51viz34",
      "img": "icons/svg/item-bag.svg",
      "effects": [],
      "folder": null,
      "sort": 0,
      "flags": {},
      "system": {
        "layers": "",
        "armorQuality": 0,
        "blunt": 0,
        "edged": 0,
        "piercing": 0,
        "fire": 0,
        "isFumble": false,
        "isStumble": true,
        "isAmputate": true,
        "impactType": "knee",
        "effectiveImpact": {
          "ei1": "M1",
          "ei5": "S2",
          "ei9": "S3",
          "ei13": "G4",
          "ei17": "G5"
        },
        "probWeight": {
          "high": 0,
          "mid": 10,
          "low": 40
        }
      },
      "ownership": {
        "default": 0
      },
      "_stats": {
        "systemId": null,
        "systemVersion": null,
        "coreVersion": null,
        "createdTime": null,
        "modifiedTime": null,
        "lastModifiedBy": null
      },
      "_key": "!actors.items!78QD3CkEWFGwFie3.cl22to1qg51viz34"
    },
    {
      "name": "Right Knee",
      "type": "armorlocation",
      "_id": "vpawezmhgcflb4ds",
      "img": "icons/svg/item-bag.svg",
      "effects": [],
      "folder": null,
      "sort": 0,
      "flags": {},
      "system": {
        "layers": "",
        "armorQuality": 0,
        "blunt": 0,
        "edged": 0,
        "piercing": 0,
        "fire": 0,
        "isFumble": false,
        "isStumble": true,
        "isAmputate": true,
        "impactType": "knee",
        "effectiveImpact": {
          "ei1": "M1",
          "ei5": "S2",
          "ei9": "S3",
          "ei13": "G4",
          "ei17": "G5"
        },
        "probWeight": {
          "high": 0,
          "mid": 10,
          "low": 40
        }
      },
      "ownership": {
        "default": 0
      },
      "_stats": {
        "systemId": null,
        "systemVersion": null,
        "coreVersion": null,
        "createdTime": null,
        "modifiedTime": null,
        "lastModifiedBy": null
      },
      "_key": "!actors.items!78QD3CkEWFGwFie3.vpawezmhgcflb4ds"
    },
    {
      "name": "Left Calf",
      "type": "armorlocation",
      "_id": "v07c938oaglkoglt",
      "img": "icons/svg/item-bag.svg",
      "effects": [],
      "folder": null,
      "sort": 0,
      "flags": {},
      "system": {
        "layers": "",
        "armorQuality": 0,
        "blunt": 0,
        "edged": 0,
        "piercing": 0,
        "fire": 0,
        "isFumble": false,
        "isStumble": true,
        "isAmputate": true,
        "impactType": "calf",
        "effectiveImpact": {
          "ei1": "M1",
          "ei5": "M1",
          "ei9": "S2",
          "ei13": "S3",
          "ei17": "G4"
        },
        "probWeight": {
          "high": 0,
          "mid": 30,
          "low": 70
        }
      },
      "ownership": {
        "default": 0
      },
      "_stats": {
        "systemId": null,
        "systemVersion": null,
        "coreVersion": null,
        "createdTime": null,
        "modifiedTime": null,
        "lastModifiedBy": null
      },
      "_key": "!actors.items!78QD3CkEWFGwFie3.v07c938oaglkoglt"
    },
    {
      "name": "Right Calf",
      "type": "armorlocation",
      "_id": "omzuisnvsde9d9e2",
      "img": "icons/svg/item-bag.svg",
      "effects": [],
      "folder": null,
      "sort": 0,
      "flags": {},
      "system": {
        "layers": "",
        "armorQuality": 0,
        "blunt": 0,
        "edged": 0,
        "piercing": 0,
        "fire": 0,
        "isFumble": false,
        "isStumble": true,
        "isAmputate": true,
        "impactType": "calf",
        "effectiveImpact": {
          "ei1": "M1",
          "ei5": "M1",
          "ei9": "S2",
          "ei13": "S3",
          "ei17": "G4"
        },
        "probWeight": {
          "high": 0,
          "mid": 30,
          "low": 70
        }
      },
      "ownership": {
        "default": 0
      },
      "_stats": {
        "systemId": null,
        "systemVersion": null,
        "coreVersion": null,
        "createdTime": null,
        "modifiedTime": null,
        "lastModifiedBy": null
      },
      "_key": "!actors.items!78QD3CkEWFGwFie3.omzuisnvsde9d9e2"
    },
    {
      "type": "armorlocation",
      "name": "Left Foot",
      "_id": "v0ovc5063pmvy61b",
      "img": "icons/svg/item-bag.svg",
      "effects": [],
      "folder": null,
      "sort": 0,
      "flags": {},
      "system": {
        "layers": "",
        "armorQuality": 0,
        "blunt": 0,
        "edged": 0,
        "piercing": 0,
        "fire": 0,
        "isFumble": false,
        "isStumble": true,
        "isAmputate": true,
        "impactType": "foot",
        "effectiveImpact": {
          "ei1": "M1",
          "ei5": "S2",
          "ei9": "S3",
          "ei13": "G4",
          "ei17": "G5"
        },
        "probWeight": {
          "high": 0,
          "mid": 20,
          "low": 40
        }
      },
      "ownership": {
        "default": 0
      },
      "_stats": {
        "systemId": null,
        "systemVersion": null,
        "coreVersion": null,
        "createdTime": null,
        "modifiedTime": null,
        "lastModifiedBy": null
      },
      "_key": "!actors.items!78QD3CkEWFGwFie3.v0ovc5063pmvy61b"
    },
    {
      "type": "armorlocation",
      "name": "Right Foot",
      "_id": "n63tcvq74nl68hjm",
      "img": "icons/svg/item-bag.svg",
      "effects": [],
      "folder": null,
      "sort": 0,
      "flags": {},
      "system": {
        "layers": "",
        "armorQuality": 0,
        "blunt": 0,
        "edged": 0,
        "piercing": 0,
        "fire": 0,
        "isFumble": false,
        "isStumble": true,
        "isAmputate": true,
        "impactType": "foot",
        "effectiveImpact": {
          "ei1": "M1",
          "ei5": "S2",
          "ei9": "S3",
          "ei13": "G4",
          "ei17": "G5"
        },
        "probWeight": {
          "high": 0,
          "mid": 20,
          "low": 40
        }
      },
      "ownership": {
        "default": 0
      },
      "_stats": {
        "systemId": null,
        "systemVersion": null,
        "coreVersion": null,
        "createdTime": null,
        "modifiedTime": null,
        "lastModifiedBy": null
      },
      "_key": "!actors.items!78QD3CkEWFGwFie3.n63tcvq74nl68hjm"
    },
    {
      "type": "miscgear",
      "img": "systems/hm3/images/icons/svg/coins.svg",
      "name": "Pence",
      "_id": "j63khdqptg7ton6f",
      "effects": [],
      "folder": null,
      "sort": 0,
      "flags": {},
      "system": {
        "notes": "",
        "description": "",
        "source": "",
        "macros": {
          "type": "script",
          "command": ""
        },
        "quantity": 12,
        "value": 1,
        "weight": 0.004,
        "isCarried": true,
        "isEquipped": true,
        "container": "on-person",
        "arcane": {
          "isArtifact": false,
          "isAttuned": false,
          "charges": -1,
          "ego": 0
        }
      },
      "ownership": {
        "default": 0
      },
      "_stats": {
        "systemId": null,
        "systemVersion": null,
        "coreVersion": null,
        "createdTime": null,
        "modifiedTime": null,
        "lastModifiedBy": null
      },
      "_key": "!actors.items!78QD3CkEWFGwFie3.j63khdqptg7ton6f"
    }
  ],
  "effects": [],
  "folder": null,
  "sort": 0,
  "flags": {},
  "_id": "78QD3CkEWFGwFie3",
  "system": {
    "bioImage": "modules/hm3-fffv1/images/FFF_606-1_Priestess_Naveh.jpg",
    "species": "Human",
    "fatigue": 0,
    "sunsign": "Tarael",
    "abilities": {
      "strength": {
        "base": 8
      },
      "stamina": {
        "base": 9
      },
      "dexterity": {
        "base": 11
      },
      "agility": {
        "base": 12
      },
      "intelligence": {
        "base": 16
      },
      "aura": {
        "base": 13
      },
      "will": {
        "base": 14
      },
      "eyesight": {
        "base": 13
      },
      "hearing": {
        "base": 7
      },
      "smell": {
        "base": 14
      },
      "voice": {
        "base": 13
      },
      "comeliness": {
        "base": 10
      },
      "morality": {
        "base": 8
      },
      "endurance": {
        "base": 10
      }
    },
    "move": {
      "base": 12
    },
    "shockIndex": {
      "max": 100,
      "value": 100
    },
    "description": "<table style=\"width: 95%; color: #191813; font-size: 13px;\" border=\"1\"><tbody style=\"box-sizing: border-box;\"><tr><td style=\"width: 145px;\"><strong>Apparent Age</strong></td><td>Adult</td></tr><tr><td style=\"width: 145px;\"><strong>Culture</strong></td><td>Feudal</td></tr><tr><td style=\"width: 145px;\"><strong>Social Class</strong></td><td>Freeman (unguilded)</td></tr><tr><td style=\"width: 145px;\"><strong>Height</strong></td><td>5 ft 1 in</td></tr><tr><td style=\"width: 145px;\"><strong>Frame</strong></td><td>Medium</td></tr><tr><td style=\"width: 145px;\"><strong>Weight</strong></td><td>127 lb</td></tr><tr><td style=\"width: 145px;\"><strong>Appearance</strong></td><td>Average</td></tr><tr><td style=\"width: 145px;\"><strong>Hair Colour</strong></td><td>Brown</td></tr><tr><td style=\"width: 145px;\"><strong>Eye Colour</strong></td><td>Hazel</td></tr><tr><td style=\"width: 145px;\"><strong>Voice</strong></td><td>Pleasant</td></tr><tr><td style=\"width: 145px;\"><strong>Obvious Medical Traits</strong></td><td>None</td></tr><tr><td style=\"width: 145px;\"><strong>Apparent Occupation</strong></td><td>Cook / servant</td></tr><tr><td style=\"width: 145px;\"><strong>Apparent Wealth</strong></td><td>Little</td></tr><tr><td style=\"width: 145px;\"><strong>Weapons</strong></td><td>Knife</td></tr><tr><td style=\"width: 145px;\"><strong>Armour</strong></td><td>None</td></tr><tr><td style=\"width: 145px;\"><strong>Companions</strong></td><td>Andel, his scribe, manservant and two men-at-arms</td></tr><tr><td style=\"width: 145px;\"><strong>Other obvious features</strong></td><td>None</td></tr></tbody></table>",
    "biography": "<table style=\"width: 95%; color: #191813; font-size: 13px;\" border=\"1\"><tbody style=\"box-sizing: border-box;\"><tr><td style=\"width: 145px;\"><strong>Title</strong></td><td>FFF 606-1 Priestess Naveh</td></tr><tr><td style=\"width: 145px;\"><strong>Birthday</strong></td><td>17 Halane 692</td></tr><tr><td style=\"width: 145px;\"><strong>Appearance</strong></td><td>Age 27, height 5’ 1”, medium frame, weight 127 lb, average appearance, medium complexion, brown hair, hazel eyes</td></tr><tr><td style=\"width: 145px;\"><strong>Medical/Psyche</strong></td><td>Deaf in right ear, left-handed</td></tr><tr><td style=\"width: 145px;\"><strong>Size</strong></td><td>5</td></tr><tr><td style=\"width: 145px;\"><strong>Armor</strong></td><td>Wool scarf, tunic and leggings, leather shoes, knife</td></tr><tr><td style=\"width: 145px;\"><strong>Other Equipment</strong></td><td>14 doses of Leortevald (poison), 12 doses of Gaethipa (poison), and 6 doses of Yulpris (antidote)</td></tr><tr><td style=\"width: 145px;\"><strong>Valuables</strong></td><td>12d in silver in a money pouch, 30d hidden in her spice jars</td></tr><tr><td style=\"width: 145px;\"><strong>Notes</strong></td><td></td></tr></tbody></table><h2>Biography</h2><p>In 714, on the recommendation of a ‘friend’, Andel Gebar, Permanent Secretary to the Chief Clerk of the Exchequer, hired Riatha as his servant. She acts as his cook, body servant, chambermaid and washerwoman. Riatha has proven to be an excellent choice. She is friendly, outgoing, happy go lucky and is always quick with the complement. Her approachability, empathy and pleasant voice quickly lull people into her confidence. She is ‘loyal,’ never talks back, does her chores quickly and efficiently and without complaint. Although she is ‘illiterate’ and ‘not too bright,’ that is to be expected of a simple serving woman. She is a good cook and works cheaply; those are the most important things.</p><p>Riatha’s appearance, mannerisms and demeanor are skilled deceptions. She is actually a priestess of Naveh and a covert agent. Kidnapped as an infant, she was raised in the church. During the ritual stalking combat to become a priestess, she was stabbed in the right ear, causing her to become deaf on that side. She gutted her opponent without mercy or second thought. After becoming a priestess, the Garana (High Priest) dispatched her to infiltrate the royal bureaucracy. She provides detailed intelligence about persons and activities within the court through covert contacts. Riatha rarely drops her act, even during infrequent moments of complete privacy, always conscious that someone could discover her. Twice, she has been forced to act quickly and decisively to “tie-up” loose ends (including an overly inquisitive man-at-arms).  She is skilled with a dagger, though poison is her preferred weapon. Andel is complete unaware that Riatha has addicted him to Leortevald, a rare poison for which withdrawal is fatal. She doses him regularly. Should something happen to her, he will die within the week.</p><p>Unfortunately for Riatha, her life has recently taken an unexpected and perplexing twist. Andel hired a new servant, Dramin. For the first time in her life, she has met someone who truly cares for her, awakening conflicting and previously unknown feelings. This scares her, because even if personally ordered by the Garana, she could never harm Dramin.</p><h2>Adventure Hooks</h2><p>That is strange. During a secret and/or illegal operations, the PCs accidentally spot Riatha meeting one of her Navehan contacts. She notices them and a game of cat and mouse begins. The PCs should be very careful.</p><p>For her own reasons. The PCs get themselves is a very serious bind. For reasons known only to Riatha, she assists them escape etc. However, afterwards, she needs a favour in return. This favour could be fatal to the PCs!</p><h2>Credits</h2><p>This character is taken from “Friends, Foes, and Followers, Vol. 1” on Lythia.com (https://www.lythia.com/game_aides/friends-foes-followers-volume-1/), by Kerry Mould, with illustrations by Richard Luscheck and Juha Makkonen, and is “fanon”, a derivative work of copyrighted material by Columbia Games Inc. and N. Robin Crossby.</p>",
    "macros": {
      "type": "script",
      "command": ""
    },
    "gender": "Female",
    "occupation": "Navehan Priestess"
  },
  "ownership": {
    "default": 0,
    "GQFkK1Ng8wDWHlCC": 3
  },
  "prototypeToken": {
    "name": "606-1 Priestess Naveh - Riatha Deherne",
    "displayName": 0,
    "actorLink": false,
    "width": 1,
    "height": 1,
    "lockRotation": false,
    "rotation": 0,
    "alpha": 1,
    "disposition": -1,
    "displayBars": 0,
    "bar1": {
      "attribute": "shockIndex"
    },
    "bar2": {
      "attribute": null
    },
    "flags": {},
    "randomImg": false,
    "light": {
      "dim": 0,
      "bright": 0,
      "angle": 360,
      "alpha": 0.25,
      "animation": {
        "speed": 5,
        "intensity": 5,
        "type": null,
        "reverse": false
      },
      "color": null,
      "coloration": 1,
      "attenuation": 0.5,
      "luminosity": 0.5,
      "saturation": 0,
      "contrast": 0,
      "shadows": 0,
      "darkness": {
        "min": 0,
        "max": 1
      }
    },
    "texture": {
      "src": "modules/hm3-fffv1/images/token/FFF_606-1_Priestess_Naveh.png",
      "scaleX": 1,
      "scaleY": 1,
      "offsetX": 0,
      "offsetY": 0,
      "rotation": 0,
      "tint": null
    },
    "sight": {
      "angle": 360,
      "enabled": false,
      "range": 0,
      "brightness": 1,
      "color": null,
      "attenuation": 0.1,
      "saturation": 0,
      "contrast": 0,
      "visionMode": "basic"
    }
  },
  "_stats": {
    "systemId": null,
    "systemVersion": null,
    "coreVersion": null,
    "createdTime": null,
    "modifiedTime": null,
    "lastModifiedBy": null
  },
  "_key": "!actors!78QD3CkEWFGwFie3"
}
